{"version":1,"staff":[{"id":"mig0001780106","name":"Alicia Clarissa De Sugar","jabatan":"CEO","active":true},{"id":"mig00022adcf8","name":"Ael De Lucha","jabatan":"DIREKTUR","active":true},{"id":"mig0003b72fb5","name":"Leviathan desugar Roseveil","jabatan":"CO-ASS","active":true},{"id":"mig0004694f16","name":"CATALINA DE SUGAR","jabatan":"CO-ASS","active":true},{"id":"mig0005df989a","name":"Kiyan Nagasaki","jabatan":"CO-ASS","active":true},{"id":"mig00069a6014","name":"Jarvis Immanuel Wibowo","jabatan":"TRAINEE","active":true},{"id":"mig000741da7f","name":"Billie Triazdy MihuMihu Wibowo","jabatan":"TRAINEE","active":true},{"id":"mig0008655579","name":"Vynara Noir Wibowo","jabatan":"TRAINEE","active":true},{"id":"mig0009aac2e3","name":"Arlan Turvass","jabatan":"TRAINEE","active":true},{"id":"mig000adc0b9a","name":"Divta De Sugar","jabatan":"TRAINEE","active":true},{"id":"mig000b601507","name":"Cyra Himari","jabatan":"TRAINEE","active":true}],"week":{"key":"2026-06-15","start":"2026-06-15","end":"2026-06-21","records":[{"id":"mig3043557407","staffId":"mig0009aac2e3","name":"Arlan Turvass","jabatan":"TRAINEE","division":"STAFF MEDIS","date":"2026-06-15","shift":"Shift 1","on":"20:30","off":"22:50","seconds":8400,"ts":1781456460000},{"id":"mig3044821eb1","staffId":"mig0004694f16","name":"Catalina De Sugar","jabatan":"CO-ASS","division":"STAFF MEDIS","date":"2026-06-15","shift":"Shift 1","on":"00:00","off":"00:10","seconds":600,"ts":1781456460000},{"id":"mig3045371231","staffId":"mig0009aac2e3","name":"Arlan Turvass","jabatan":"TRAINEE","division":"STAFF MEDIS","date":"2026-06-16","shift":"Shift 1","on":"05:10","off":"07:03","seconds":6780,"ts":1781542860000},{"id":"mig304601026f","staffId":"mig0009aac2e3","name":"Arlan Turvass","jabatan":"TRAINEE","division":"STAFF MEDIS","date":"2026-06-16","shift":"Shift 2","on":"13:55","off":"15:03","seconds":4080,"ts":1781542920000},{"id":"mig304774d5ca","staffId":"mig0009aac2e3","name":"Arlan Turvass","jabatan":"TRAINEE","division":"STAFF MEDIS","date":"2026-06-17","shift":"Shift 1","on":"14:04","off":"16:00","seconds":6960,"ts":1781629260000},{"id":"mig30484eaafa","staffId":"mig000741da7f","name":"Billie Triazdy MihuMihu Wibowo","jabatan":"TRAINEE","division":"STAFF MEDIS","date":"2026-06-17","shift":"Shift 1","on":"13:20","off":"15:22","seconds":7320,"ts":1781629260000},{"id":"mig304995d33e","staffId":"mig000741da7f","name":"Billie Triazdy MihuMihu Wibowo","jabatan":"TRAINEE","division":"STAFF MEDIS","date":"2026-06-17","shift":"Shift 2","on":"19:18","off":"23:59","seconds":16860,"ts":1781629320000},{"id":"mig304aa3363b","staffId":"mig0004694f16","name":"Catalina De Sugar","jabatan":"CO-ASS","division":"STAFF MEDIS","date":"2026-06-17","shift":"Shift 1","on":"19:00","off":"22:30","seconds":12600,"ts":1781629260000},{"id":"mig304b92f843","staffId":"mig00069a6014","name":"Jarvis Immanuel Wibowo","jabatan":"TRAINEE","division":"STAFF MEDIS","date":"2026-06-17","shift":"Shift 1","on":"13:20","off":"14:30","seconds":4200,"ts":1781629260000},{"id":"mig304cba00ec","staffId":"mig00069a6014","name":"Jarvis Immanuel Wibowo","jabatan":"TRAINEE","division":"STAFF MEDIS","date":"2026-06-17","shift":"Shift 2","on":"21:35","off":"23:59","seconds":8640,"ts":1781629320000},{"id":"mig304de55fd6","staffId":"","name":"Pey'D Carrera","jabatan":"TRAINEE","division":"STAFF MEDIS","date":"2026-06-17","shift":"Shift 1","on":"19:40","off":"20:55","seconds":4500,"ts":1781629260000},{"id":"mig304eb6053f","staffId":"mig0008655579","name":"Vynara Noir Wibowo","jabatan":"TRAINEE","division":"STAFF MEDIS","date":"2026-06-17","shift":"Shift 1","on":"13:20","off":"15:25","seconds":7500,"ts":1781629260000},{"id":"mig304fb2de9a","staffId":"mig0009aac2e3","name":"Arlan Turvass","jabatan":"TRAINEE","division":"STAFF MEDIS","date":"2026-06-18","shift":"Shift 1","on":"12:42","off":"15:01","seconds":8340,"ts":1781715660000},{"id":"mig305019341e","staffId":"mig0009aac2e3","name":"Arlan Turvass","jabatan":"TRAINEE","division":"STAFF MEDIS","date":"2026-06-18","shift":"Shift 2","on":"20:40","off":"21:56","seconds":4560,"ts":1781715720000},{"id":"mig30511087dc","staffId":"mig000741da7f","name":"Billie Triazdy MihuMihu Wibowo","jabatan":"TRAINEE","division":"STAFF MEDIS","date":"2026-06-18","shift":"Shift 1","on":"00:00","off":"00:18","seconds":1080,"ts":1781715660000},{"id":"mig3052a65e8f","staffId":"mig000741da7f","name":"Billie Triazdy MihuMihu Wibowo","jabatan":"TRAINEE","division":"STAFF MEDIS","date":"2026-06-18","shift":"Shift 2","on":"17:40","off":"21:08","seconds":12480,"ts":1781715720000},{"id":"mig30535ee144","staffId":"mig000adc0b9a","name":"Divta De Sugar","jabatan":"TRAINEE","division":"STAFF MEDIS","date":"2026-06-18","shift":"Shift 1","on":"22:30","off":"23:59","seconds":5340,"ts":1781715660000},{"id":"mig3054ab22c7","staffId":"mig00069a6014","name":"Jarvis Immanuel Wibowo","jabatan":"TRAINEE","division":"STAFF MEDIS","date":"2026-06-18","shift":"Shift 1","on":"00:00","off":"00:18","seconds":1080,"ts":1781715660000},{"id":"mig3055657389","staffId":"mig0008655579","name":"Vynara Noir Wibowo","jabatan":"TRAINEE","division":"STAFF MEDIS","date":"2026-06-18","shift":"Shift 1","on":"17:55","off":"21:15","seconds":12000,"ts":1781715660000},{"id":"mig30560322d4","staffId":"mig0009aac2e3","name":"Arlan Turvass","jabatan":"TRAINEE","division":"STAFF MEDIS","date":"2026-06-19","shift":"Shift 1","on":"19:29","off":"21:56","seconds":8820,"ts":1781802060000},{"id":"mig3057440c8d","staffId":"mig000741da7f","name":"Billie Triazdy MihuMihu Wibowo","jabatan":"TRAINEE","division":"STAFF MEDIS","date":"2026-06-19","shift":"Shift 1","on":"14:29","off":"15:23","seconds":3240,"ts":1781802060000},{"id":"mig305858b2b4","staffId":"mig000741da7f","name":"Billie Triazdy MihuMihu Wibowo","jabatan":"TRAINEE","division":"STAFF MEDIS","date":"2026-06-19","shift":"Shift 2","on":"19:52","off":"20:35","seconds":2580,"ts":1781802120000},{"id":"mig30595f1a94","staffId":"mig0004694f16","name":"Catalina De Sugar","jabatan":"CO-ASS","division":"STAFF MEDIS","date":"2026-06-19","shift":"Shift 1","on":"17:10","off":"17:48","seconds":2280,"ts":1781802060000},{"id":"mig305a3bbcdb","staffId":"mig0004694f16","name":"Catalina De Sugar","jabatan":"CO-ASS","division":"STAFF MEDIS","date":"2026-06-19","shift":"Shift 2","on":"19:32","off":"23:59","seconds":16020,"ts":1781802120000},{"id":"mig305ba084ee","staffId":"mig000adc0b9a","name":"Divta De Sugar","jabatan":"TRAINEE","division":"STAFF MEDIS","date":"2026-06-19","shift":"Shift 1","on":"00:00","off":"02:07","seconds":7620,"ts":1781802060000},{"id":"mig305cfeb4e6","staffId":"mig000adc0b9a","name":"Divta De Sugar","jabatan":"TRAINEE","division":"STAFF MEDIS","date":"2026-06-19","shift":"Shift 2","on":"15:15","off":"16:20","seconds":3900,"ts":1781802120000},{"id":"mig305de739c5","staffId":"mig00069a6014","name":"Jarvis Immanuel Wibowo","jabatan":"TRAINEE","division":"STAFF MEDIS","date":"2026-06-19","shift":"Shift 1","on":"00:00","off":"00:18","seconds":1080,"ts":1781802060000},{"id":"mig305eea3689","staffId":"mig0008655579","name":"Vynara Noir Wibowo","jabatan":"TRAINEE","division":"STAFF MEDIS","date":"2026-06-19","shift":"Shift 1","on":"19:52","off":"20:35","seconds":2580,"ts":1781802060000},{"id":"mig305ff956e5","staffId":"mig0004694f16","name":"Catalina De Sugar","jabatan":"CO-ASS","division":"STAFF MEDIS","date":"2026-06-20","shift":"Shift 1","on":"00:00","off":"01:30","seconds":5400,"ts":1781888460000},{"id":"mig3060cf821d","staffId":"mig000b601507","name":"Cyra Himari","jabatan":"TRAINEE","division":"STAFF MEDIS","date":"2026-06-20","shift":"Shift 1","on":"21:19","off":"23:59","seconds":9600,"ts":1781888460000},{"id":"mig306196c597","staffId":"mig000adc0b9a","name":"Divta De Sugar","jabatan":"TRAINEE","division":"STAFF MEDIS","date":"2026-06-20","shift":"Shift 1","on":"01:20","off":"02:30","seconds":4200,"ts":1781888460000},{"id":"mig3062fccc69","staffId":"mig0001780106","name":"Alicia Clarissa De Sugar","jabatan":"CEO","division":"DIREKSI & MANAJEMEN","date":"2026-06-21","shift":"Shift 1","on":"12:00","off":"14:00","seconds":7200,"ts":1781974860000},{"id":"mig30632710c2","staffId":"mig000741da7f","name":"Billie Triazdy MihuMihu Wibowo","jabatan":"TRAINEE","division":"STAFF MEDIS","date":"2026-06-21","shift":"Shift 1","on":"01:00","off":"02:02","seconds":3720,"ts":1781974860000},{"id":"mig3064860f60","staffId":"mig000b601507","name":"Cyra Himari","jabatan":"TRAINEE","division":"STAFF MEDIS","date":"2026-06-21","shift":"Shift 1","on":"00:00","off":"01:39","seconds":5940,"ts":1781974860000},{"id":"mig306567587c","staffId":"mig000adc0b9a","name":"Divta De Sugar","jabatan":"TRAINEE","division":"STAFF MEDIS","date":"2026-06-21","shift":"Shift 1","on":"02:52","off":"04:20","seconds":5280,"ts":1781974860000},{"id":"mig306608340e","staffId":"mig00069a6014","name":"Jarvis Immanuel Wibowo","jabatan":"TRAINEE","division":"STAFF MEDIS","date":"2026-06-21","shift":"Shift 1","on":"00:10","off":"01:55","seconds":6300,"ts":1781974860000},{"id":"mig3067ea6ae7","staffId":"mig0008655579","name":"Vynara Noir Wibowo","jabatan":"TRAINEE","division":"STAFF MEDIS","date":"2026-06-21","shift":"Shift 1","on":"01:00","off":"02:02","seconds":3720,"ts":1781974860000}]},"history":[{"key":"2026-04-20","start":"2026-04-20","end":"2026-04-26","records":[{"id":"mig2eabd637f9","staffId":"","name":"Armel Quantum","jabatan":"TRAINEE","division":"STAFF MEDIS","date":"2026-04-20","shift":"Shift 1","on":"15:00","off":"17:00","seconds":7200,"ts":1776618060000},{"id":"mig2eac04f3be","staffId":"","name":"Armel Quantum","jabatan":"TRAINEE","division":"STAFF MEDIS","date":"2026-04-20","shift":"Shift 2","on":"19:30","off":"23:59","seconds":16140,"ts":1776618120000},{"id":"mig2eade6ae85","staffId":"","name":"Draco Hidayat Hawkins","jabatan":"SEKBEN","division":"DIREKSI & MANAJEMEN","date":"2026-04-20","shift":"Shift 1","on":"00:01","off":"02:32","seconds":9060,"ts":1776618060000},{"id":"mig2eae682c75","staffId":"","name":"Draco Hidayat Hawkins","jabatan":"SEKBEN","division":"DIREKSI & MANAJEMEN","date":"2026-04-20","shift":"Shift 2","on":"21:32","off":"23:59","seconds":8820,"ts":1776618120000},{"id":"mig2eaf7ac331","staffId":"","name":"Dyvetta O. Kratawijaya","jabatan":"TRAINEE","division":"STAFF MEDIS","date":"2026-04-20","shift":"Shift 1","on":"13:50","off":"16:55","seconds":11100,"ts":1776618060000},{"id":"mig2eb0da304b","staffId":"","name":"Ellena Snorris","jabatan":"DOKTER SPESIALIS","division":"STAFF MEDIS","date":"2026-04-20","shift":"Shift 1","on":"18:32","off":"19:30","seconds":3480,"ts":1776618060000},{"id":"mig2eb1dc3013","staffId":"","name":"Fae Bellen","jabatan":"HRD","division":"DIREKSI & MANAJEMEN","date":"2026-04-20","shift":"Shift 1","on":"12:59","off":"15:06","seconds":7620,"ts":1776618060000},{"id":"mig2eb233e508","staffId":"","name":"LEON DACOSTA","jabatan":"TRAINEE","division":"STAFF MEDIS","date":"2026-04-20","shift":"Shift 1","on":"00:20","off":"02:25","seconds":7500,"ts":1776618060000},{"id":"mig2eb39eb07d","staffId":"","name":"RICKLONA DIAZEPAM","jabatan":"KOMDIS","division":"DIREKSI & MANAJEMEN","date":"2026-04-20","shift":"Shift 1","on":"21:35","off":"23:59","seconds":8640,"ts":1776618060000},{"id":"mig2eb4208bb2","staffId":"","name":"Viktor Moriarty","jabatan":"TRAINEE","division":"STAFF MEDIS","date":"2026-04-20","shift":"Shift 1","on":"11:20","off":"13:23","seconds":7380,"ts":1776618060000},{"id":"mig2eb58f3541","staffId":"","name":"Viktor Moriarty","jabatan":"TRAINEE","division":"STAFF MEDIS","date":"2026-04-20","shift":"Shift 2","on":"13:38","off":"16:30","seconds":10320,"ts":1776618120000},{"id":"mig2eb6d43739","staffId":"","name":"Armel Quantum","jabatan":"TRAINEE","division":"STAFF MEDIS","date":"2026-04-21","shift":"Shift 1","on":"14:31","off":"16:32","seconds":7260,"ts":1776704460000},{"id":"mig2eb7319950","staffId":"","name":"Armel Quantum","jabatan":"TRAINEE","division":"STAFF MEDIS","date":"2026-04-21","shift":"Shift 2","on":"19:15","off":"23:00","seconds":13500,"ts":1776704520000},{"id":"mig2eb8c4b7e5","staffId":"","name":"Draco Hidayat Hawkins","jabatan":"SEKBEN","division":"DIREKSI & MANAJEMEN","date":"2026-04-21","shift":"Shift 1","on":"00:01","off":"01:21","seconds":4800,"ts":1776704460000},{"id":"mig2eb979f2dc","staffId":"","name":"Draco Hidayat Hawkins","jabatan":"SEKBEN","division":"DIREKSI & MANAJEMEN","date":"2026-04-21","shift":"Shift 2","on":"21:14","off":"23:59","seconds":9900,"ts":1776704520000},{"id":"mig2ebaa29e06","staffId":"","name":"Dyvetta O. Kratawijaya","jabatan":"TRAINEE","division":"STAFF MEDIS","date":"2026-04-21","shift":"Shift 1","on":"19:50","off":"22:20","seconds":9000,"ts":1776704460000},{"id":"mig2ebb95600f","staffId":"","name":"Ellena Snorris","jabatan":"DOKTER SPESIALIS","division":"STAFF MEDIS","date":"2026-04-21","shift":"Shift 1","on":"21:10","off":"23:53","seconds":9780,"ts":1776704460000},{"id":"mig2ebc3c949c","staffId":"","name":"Ellena Snorris","jabatan":"DOKTER SPESIALIS","division":"STAFF MEDIS","date":"2026-04-21","shift":"Shift 2","on":"21:37","off":"23:32","seconds":6900,"ts":1776704520000},{"id":"mig2ebd5611aa","staffId":"","name":"Fae Bellen","jabatan":"HRD","division":"DIREKSI & MANAJEMEN","date":"2026-04-21","shift":"Shift 1","on":"12:24","off":"13:42","seconds":4680,"ts":1776704460000},{"id":"mig2ebe65f55a","staffId":"","name":"Grizelle D Whitegate","jabatan":"KOMDIS","division":"DIREKSI & MANAJEMEN","date":"2026-04-21","shift":"Shift 1","on":"20:05","off":"23:59","seconds":14040,"ts":1776704460000},{"id":"mig2ebf4aed74","staffId":"","name":"Jonathan Edward Sawyer Kylan Hudson","jabatan":"TRAINEE","division":"STAFF MEDIS","date":"2026-04-21","shift":"Shift 1","on":"15:56","off":"17:03","seconds":4020,"ts":1776704460000},{"id":"mig2ec0867034","staffId":"","name":"Jonathan Edward Sawyer Kylan Hudson","jabatan":"TRAINEE","division":"STAFF MEDIS","date":"2026-04-21","shift":"Shift 2","on":"19:38","off":"20:52","seconds":4440,"ts":1776704520000},{"id":"mig2ec1216240","staffId":"","name":"LEON DACOSTA","jabatan":"TRAINEE","division":"STAFF MEDIS","date":"2026-04-21","shift":"Shift 1","on":"21:10","off":"23:40","seconds":9000,"ts":1776704460000},{"id":"mig2ec2892cbb","staffId":"","name":"LEON DACOSTA","jabatan":"TRAINEE","division":"STAFF MEDIS","date":"2026-04-21","shift":"Shift 2","on":"23:50","off":"23:59","seconds":540,"ts":1776704520000},{"id":"mig2ec3588fac","staffId":"","name":"Lord Shuel","jabatan":"HRD","division":"DIREKSI & MANAJEMEN","date":"2026-04-21","shift":"Shift 1","on":"14:02","off":"17:06","seconds":11040,"ts":1776704460000},{"id":"mig2ec4b9a768","staffId":"","name":"Noah Esvander","jabatan":"TRAINEE","division":"STAFF MEDIS","date":"2026-04-21","shift":"Shift 1","on":"22:02","off":"23:00","seconds":3480,"ts":1776704460000},{"id":"mig2ec56ce0c4","staffId":"","name":"RICKLONA DIAZEPAM","jabatan":"KOMDIS","division":"DIREKSI & MANAJEMEN","date":"2026-04-21","shift":"Shift 1","on":"14:26","off":"17:08","seconds":9720,"ts":1776704460000},{"id":"mig2ec6dbaf2e","staffId":"","name":"RICKLONA DIAZEPAM","jabatan":"KOMDIS","division":"DIREKSI & MANAJEMEN","date":"2026-04-21","shift":"Shift 2","on":"19:23","off":"23:59","seconds":16560,"ts":1776704520000},{"id":"mig2ec77b9e44","staffId":"","name":"luxii de voltre","jabatan":"TRAINEE","division":"STAFF MEDIS","date":"2026-04-21","shift":"Shift 1","on":"22:00","off":"23:00","seconds":3600,"ts":1776704460000},{"id":"mig2ec89f7797","staffId":"","name":"Armel Quantum","jabatan":"TRAINEE","division":"STAFF MEDIS","date":"2026-04-22","shift":"Shift 1","on":"18:35","off":"22:30","seconds":14100,"ts":1776790860000},{"id":"mig2ec939a3cd","staffId":"","name":"Draco Hidayat Hawkins","jabatan":"SEKBEN","division":"DIREKSI & MANAJEMEN","date":"2026-04-22","shift":"Shift 1","on":"00:01","off":"00:41","seconds":2400,"ts":1776790860000},{"id":"mig2eca3a2c77","staffId":"","name":"Draco Hidayat Hawkins","jabatan":"SEKBEN","division":"DIREKSI & MANAJEMEN","date":"2026-04-22","shift":"Shift 2","on":"21:37","off":"23:59","seconds":8520,"ts":1776790920000},{"id":"mig2ecb903a46","staffId":"","name":"Dyvetta O. Kratawijaya","jabatan":"TRAINEE","division":"STAFF MEDIS","date":"2026-04-22","shift":"Shift 1","on":"14:30","off":"16:05","seconds":5700,"ts":1776790860000},{"id":"mig2ecc8dd511","staffId":"","name":"Dyvetta O. Kratawijaya","jabatan":"TRAINEE","division":"STAFF MEDIS","date":"2026-04-22","shift":"Shift 2","on":"20:00","off":"21:05","seconds":3900,"ts":1776790920000},{"id":"mig2ecd9ecb64","staffId":"","name":"Fae Bellen","jabatan":"HRD","division":"DIREKSI & MANAJEMEN","date":"2026-04-22","shift":"Shift 1","on":"09:15","off":"10:32","seconds":4620,"ts":1776790860000},{"id":"mig2ece5dd5b3","staffId":"","name":"Grizelle D Whitegate","jabatan":"KOMDIS","division":"DIREKSI & MANAJEMEN","date":"2026-04-22","shift":"Shift 1","on":"00:00","off":"01:00","seconds":3600,"ts":1776790860000},{"id":"mig2ecff68539","staffId":"","name":"Grizelle D Whitegate","jabatan":"KOMDIS","division":"DIREKSI & MANAJEMEN","date":"2026-04-22","shift":"Shift 2","on":"20:25","off":"22:00","seconds":5700,"ts":1776790920000},{"id":"mig2ed00f460e","staffId":"","name":"Grizelle D Whitegate","jabatan":"KOMDIS","division":"DIREKSI & MANAJEMEN","date":"2026-04-22","shift":"Shift 3","on":"22:45","off":"22:55","seconds":600,"ts":1776790980000},{"id":"mig2ed1adc913","staffId":"","name":"Jonathan Edward Sawyer Kylan Hudson","jabatan":"TRAINEE","division":"STAFF MEDIS","date":"2026-04-22","shift":"Shift 1","on":"13:46","off":"16:06","seconds":8400,"ts":1776790860000},{"id":"mig2ed2241058","staffId":"","name":"Jonathan Edward Sawyer Kylan Hudson","jabatan":"TRAINEE","division":"STAFF MEDIS","date":"2026-04-22","shift":"Shift 2","on":"21:48","off":"22:31","seconds":2580,"ts":1776790920000},{"id":"mig2ed3264e4f","staffId":"","name":"LEON DACOSTA","jabatan":"TRAINEE","division":"STAFF MEDIS","date":"2026-04-22","shift":"Shift 1","on":"00:01","off":"02:06","seconds":7500,"ts":1776790860000},{"id":"mig2ed425e9af","staffId":"","name":"LEON DACOSTA","jabatan":"TRAINEE","division":"STAFF MEDIS","date":"2026-04-22","shift":"Shift 2","on":"23:56","off":"23:59","seconds":180,"ts":1776790920000},{"id":"mig2ed5e74029","staffId":"","name":"RICKLONA DIAZEPAM","jabatan":"KOMDIS","division":"DIREKSI & MANAJEMEN","date":"2026-04-22","shift":"Shift 1","on":"22:28","off":"23:59","seconds":5460,"ts":1776790860000},{"id":"mig2ed6657c45","staffId":"","name":"Viktor Moriarty","jabatan":"TRAINEE","division":"STAFF MEDIS","date":"2026-04-22","shift":"Shift 1","on":"10:25","off":"12:11","seconds":6360,"ts":1776790860000},{"id":"mig2ed703dacc","staffId":"","name":"Armel Quantum","jabatan":"TRAINEE","division":"STAFF MEDIS","date":"2026-04-23","shift":"Shift 1","on":"15:20","off":"17:00","seconds":6000,"ts":1776877260000},{"id":"mig2ed86b5e06","staffId":"","name":"Armel Quantum","jabatan":"TRAINEE","division":"STAFF MEDIS","date":"2026-04-23","shift":"Shift 2","on":"19:50","off":"22:30","seconds":9600,"ts":1776877320000},{"id":"mig2ed9fc127c","staffId":"","name":"Draco Hidayat Hawkins","jabatan":"SEKBEN","division":"DIREKSI & MANAJEMEN","date":"2026-04-23","shift":"Shift 1","on":"00:01","off":"00:41","seconds":2400,"ts":1776877260000},{"id":"mig2eda4362d4","staffId":"","name":"Dyvetta O. Kratawijaya","jabatan":"TRAINEE","division":"STAFF MEDIS","date":"2026-04-23","shift":"Shift 1","on":"14:10","off":"15:15","seconds":3900,"ts":1776877260000},{"id":"mig2edb4581c2","staffId":"","name":"Dyvetta O. Kratawijaya","jabatan":"TRAINEE","division":"STAFF MEDIS","date":"2026-04-23","shift":"Shift 2","on":"21:00","off":"23:05","seconds":7500,"ts":1776877320000},{"id":"mig2edc6a6121","staffId":"","name":"Ellena Snorris","jabatan":"DOKTER SPESIALIS","division":"STAFF MEDIS","date":"2026-04-23","shift":"Shift 1","on":"21:27","off":"22:25","seconds":3480,"ts":1776877260000},{"id":"mig2edddf0049","staffId":"","name":"Fae Bellen","jabatan":"HRD","division":"DIREKSI & MANAJEMEN","date":"2026-04-23","shift":"Shift 1","on":"12:40","off":"14:11","seconds":5460,"ts":1776877260000},{"id":"mig2ede08ae00","staffId":"","name":"LEON DACOSTA","jabatan":"TRAINEE","division":"STAFF MEDIS","date":"2026-04-23","shift":"Shift 1","on":"00:01","off":"03:04","seconds":10980,"ts":1776877260000},{"id":"mig2edf58fc1d","staffId":"","name":"RICKLONA DIAZEPAM","jabatan":"KOMDIS","division":"DIREKSI & MANAJEMEN","date":"2026-04-23","shift":"Shift 1","on":"00:00","off":"00:26","seconds":1560,"ts":1776877260000},{"id":"mig2ee09af1c1","staffId":"","name":"RICKLONA DIAZEPAM","jabatan":"KOMDIS","division":"DIREKSI & MANAJEMEN","date":"2026-04-23","shift":"Shift 2","on":"21:27","off":"23:59","seconds":9120,"ts":1776877320000},{"id":"mig2ee12523a8","staffId":"","name":"Viktor Moriarty","jabatan":"TRAINEE","division":"STAFF MEDIS","date":"2026-04-23","shift":"Shift 1","on":"11:28","off":"17:30","seconds":21720,"ts":1776877260000},{"id":"mig2ee21ccdba","staffId":"","name":"Armel Quantum","jabatan":"TRAINEE","division":"STAFF MEDIS","date":"2026-04-24","shift":"Shift 1","on":"13:10","off":"16:10","seconds":10800,"ts":1776963660000},{"id":"mig2ee31506de","staffId":"","name":"Armel Quantum","jabatan":"TRAINEE","division":"STAFF MEDIS","date":"2026-04-24","shift":"Shift 2","on":"20:59","off":"23:59","seconds":10800,"ts":1776963720000},{"id":"mig2ee43e223d","staffId":"","name":"Carellia Jianyx Whitegate","jabatan":"TRAINEE","division":"STAFF MEDIS","date":"2026-04-24","shift":"Shift 1","on":"00:03","off":"01:24","seconds":4860,"ts":1776963660000},{"id":"mig2ee52f9a6a","staffId":"","name":"Carellia Jianyx Whitegate","jabatan":"TRAINEE","division":"STAFF MEDIS","date":"2026-04-24","shift":"Shift 2","on":"21:15","off":"23:59","seconds":9840,"ts":1776963720000},{"id":"mig2ee667594f","staffId":"","name":"Ellena Snorris","jabatan":"DOKTER SPESIALIS","division":"STAFF MEDIS","date":"2026-04-24","shift":"Shift 1","on":"20:51","off":"23:59","seconds":11280,"ts":1776963660000},{"id":"mig2ee7db3c93","staffId":"","name":"Fae Bellen","jabatan":"HRD","division":"DIREKSI & MANAJEMEN","date":"2026-04-24","shift":"Shift 1","on":"22:07","off":"23:34","seconds":5220,"ts":1776963660000},{"id":"mig2ee81256b1","staffId":"","name":"Grizelle D Whitegate","jabatan":"KOMDIS","division":"DIREKSI & MANAJEMEN","date":"2026-04-24","shift":"Shift 1","on":"20:40","off":"23:35","seconds":10500,"ts":1776963660000},{"id":"mig2ee9500a83","staffId":"","name":"LEON DACOSTA","jabatan":"TRAINEE","division":"STAFF MEDIS","date":"2026-04-24","shift":"Shift 1","on":"00:03","off":"03:34","seconds":12660,"ts":1776963660000},{"id":"mig2eea397322","staffId":"","name":"LEON DACOSTA","jabatan":"TRAINEE","division":"STAFF MEDIS","date":"2026-04-24","shift":"Shift 2","on":"20:50","off":"23:59","seconds":11340,"ts":1776963720000},{"id":"mig2eeb4506ab","staffId":"","name":"Noah Esvander","jabatan":"TRAINEE","division":"STAFF MEDIS","date":"2026-04-24","shift":"Shift 1","on":"21:04","off":"23:06","seconds":7320,"ts":1776963660000},{"id":"mig2eec60b580","staffId":"","name":"RICKLONA DIAZEPAM","jabatan":"KOMDIS","division":"DIREKSI & MANAJEMEN","date":"2026-04-24","shift":"Shift 1","on":"00:00","off":"02:30","seconds":9000,"ts":1776963660000},{"id":"mig2eed424014","staffId":"","name":"Viktor Moriarty","jabatan":"TRAINEE","division":"STAFF MEDIS","date":"2026-04-24","shift":"Shift 1","on":"13:10","off":"14:08","seconds":3480,"ts":1776963660000},{"id":"mig2eee79a63e","staffId":"","name":"Armel Quantum","jabatan":"TRAINEE","division":"STAFF MEDIS","date":"2026-04-25","shift":"Shift 1","on":"12:40","off":"15:40","seconds":10800,"ts":1777050060000},{"id":"mig2eef9b4f65","staffId":"","name":"Carellia Jianyx Whitegate","jabatan":"TRAINEE","division":"STAFF MEDIS","date":"2026-04-25","shift":"Shift 1","on":"00:00","off":"00:33","seconds":1980,"ts":1777050060000},{"id":"mig2ef0306651","staffId":"","name":"Dyvetta O. Kratawijaya","jabatan":"TRAINEE","division":"STAFF MEDIS","date":"2026-04-25","shift":"Shift 1","on":"22:00","off":"23:50","seconds":6600,"ts":1777050060000},{"id":"mig2ef168a88c","staffId":"","name":"Fae Bellen","jabatan":"HRD","division":"DIREKSI & MANAJEMEN","date":"2026-04-25","shift":"Shift 1","on":"19:12","off":"23:17","seconds":14700,"ts":1777050060000},{"id":"mig2ef2b7da2a","staffId":"","name":"LEON DACOSTA","jabatan":"TRAINEE","division":"STAFF MEDIS","date":"2026-04-25","shift":"Shift 1","on":"00:01","off":"00:33","seconds":1920,"ts":1777050060000},{"id":"mig2ef3fb0342","staffId":"","name":"LEON DACOSTA","jabatan":"TRAINEE","division":"STAFF MEDIS","date":"2026-04-25","shift":"Shift 2","on":"21:50","off":"22:56","seconds":3960,"ts":1777050120000},{"id":"mig2ef4fda0f6","staffId":"","name":"Noah Esvander","jabatan":"TRAINEE","division":"STAFF MEDIS","date":"2026-04-25","shift":"Shift 1","on":"09:45","off":"11:11","seconds":5160,"ts":1777050060000},{"id":"mig2ef5b9bc7a","staffId":"","name":"RICKLONA DIAZEPAM","jabatan":"KOMDIS","division":"DIREKSI & MANAJEMEN","date":"2026-04-25","shift":"Shift 1","on":"13:51","off":"17:00","seconds":11340,"ts":1777050060000},{"id":"mig2ef61e481c","staffId":"","name":"Viktor Moriarty","jabatan":"TRAINEE","division":"STAFF MEDIS","date":"2026-04-25","shift":"Shift 1","on":"09:34","off":"15:00","seconds":19560,"ts":1777050060000},{"id":"mig2ef7cee99b","staffId":"","name":"Viktor Moriarty","jabatan":"TRAINEE","division":"STAFF MEDIS","date":"2026-04-25","shift":"Shift 2","on":"15:55","off":"16:34","seconds":2340,"ts":1777050120000},{"id":"mig2ef8eaea07","staffId":"","name":"Viktor Moriarty","jabatan":"TRAINEE","division":"STAFF MEDIS","date":"2026-04-25","shift":"Shift 3","on":"16:38","off":"16:43","seconds":300,"ts":1777050180000},{"id":"mig2ef9151cb5","staffId":"","name":"luxii de voltre","jabatan":"TRAINEE","division":"STAFF MEDIS","date":"2026-04-25","shift":"Shift 1","on":"09:45","off":"11:05","seconds":4800,"ts":1777050060000},{"id":"mig2efa1d13eb","staffId":"","name":"Armel Quantum","jabatan":"TRAINEE","division":"STAFF MEDIS","date":"2026-04-26","shift":"Shift 1","on":"19:19","off":"23:59","seconds":16800,"ts":1777136460000},{"id":"mig2efb1c8f69","staffId":"","name":"Carellia Jianyx Whitegate","jabatan":"TRAINEE","division":"STAFF MEDIS","date":"2026-04-26","shift":"Shift 1","on":"21:48","off":"23:59","seconds":7860,"ts":1777136460000},{"id":"mig2efc5e7a8c","staffId":"","name":"Dyvetta O. Kratawijaya","jabatan":"TRAINEE","division":"STAFF MEDIS","date":"2026-04-26","shift":"Shift 1","on":"21:50","off":"22:30","seconds":2400,"ts":1777136460000},{"id":"mig2efd5573f6","staffId":"","name":"Grizelle D Whitegate","jabatan":"KOMDIS","division":"DIREKSI & MANAJEMEN","date":"2026-04-26","shift":"Shift 1","on":"00:00","off":"01:40","seconds":6000,"ts":1777136460000},{"id":"mig2efea7d2df","staffId":"","name":"LEON DACOSTA","jabatan":"TRAINEE","division":"STAFF MEDIS","date":"2026-04-26","shift":"Shift 1","on":"21:55","off":"23:59","seconds":7440,"ts":1777136460000},{"id":"mig2eff538a99","staffId":"","name":"Viktor Moriarty","jabatan":"TRAINEE","division":"STAFF MEDIS","date":"2026-04-26","shift":"Shift 1","on":"07:41","off":"11:57","seconds":15360,"ts":1777136460000},{"id":"mig2f00b43bf0","staffId":"","name":"Viktor Moriarty","jabatan":"TRAINEE","division":"STAFF MEDIS","date":"2026-04-26","shift":"Shift 2","on":"12:54","off":"17:30","seconds":16560,"ts":1777136520000}],"archivedAt":1777222740000},{"key":"2026-04-27","start":"2026-04-27","end":"2026-05-03","records":[{"id":"mig2f0121e894","staffId":"","name":"Armel Quantum","jabatan":"TRAINEE","division":"STAFF MEDIS","date":"2026-04-27","shift":"Shift 1","on":"15:25","off":"17:05","seconds":6000,"ts":1777222860000},{"id":"mig2f02875e50","staffId":"","name":"Armel Quantum","jabatan":"TRAINEE","division":"STAFF MEDIS","date":"2026-04-27","shift":"Shift 2","on":"19:15","off":"21:15","seconds":7200,"ts":1777222920000},{"id":"mig2f036d992b","staffId":"","name":"Carellia Jianyx Whitegate","jabatan":"TRAINEE","division":"STAFF MEDIS","date":"2026-04-27","shift":"Shift 1","on":"00:00","off":"01:42","seconds":6120,"ts":1777222860000},{"id":"mig2f04737d09","staffId":"","name":"Carellia Jianyx Whitegate","jabatan":"TRAINEE","division":"STAFF MEDIS","date":"2026-04-27","shift":"Shift 2","on":"21:30","off":"23:38","seconds":7680,"ts":1777222920000},{"id":"mig2f055e3840","staffId":"","name":"Draco Hidayat Hawkins","jabatan":"SEKBEN","division":"DIREKSI & MANAJEMEN","date":"2026-04-27","shift":"Shift 1","on":"21:37","off":"23:29","seconds":6720,"ts":1777222860000},{"id":"mig2f06081309","staffId":"","name":"Dyvetta O. Kratawijaya","jabatan":"TRAINEE","division":"STAFF MEDIS","date":"2026-04-27","shift":"Shift 1","on":"14:10","off":"15:27","seconds":4620,"ts":1777222860000},{"id":"mig2f075560ff","staffId":"","name":"Dyvetta O. Kratawijaya","jabatan":"TRAINEE","division":"STAFF MEDIS","date":"2026-04-27","shift":"Shift 2","on":"21:25","off":"22:35","seconds":4200,"ts":1777222920000},{"id":"mig2f08437167","staffId":"","name":"Ellena Snorris","jabatan":"DOKTER SPESIALIS","division":"STAFF MEDIS","date":"2026-04-27","shift":"Shift 1","on":"21:24","off":"23:05","seconds":6060,"ts":1777222860000},{"id":"mig2f09b1eb1a","staffId":"","name":"Fae Bellen","jabatan":"HRD","division":"DIREKSI & MANAJEMEN","date":"2026-04-27","shift":"Shift 1","on":"08:25","off":"10:24","seconds":7140,"ts":1777222860000},{"id":"mig2f0a6156ff","staffId":"","name":"Fae Bellen","jabatan":"HRD","division":"DIREKSI & MANAJEMEN","date":"2026-04-27","shift":"Shift 2","on":"13:50","off":"15:54","seconds":7440,"ts":1777222920000},{"id":"mig2f0b67ec30","staffId":"","name":"Fae Bellen","jabatan":"HRD","division":"DIREKSI & MANAJEMEN","date":"2026-04-27","shift":"Shift 3","on":"19:42","off":"20:28","seconds":2760,"ts":1777222980000},{"id":"mig2f0ce8bbe4","staffId":"","name":"Grizelle D Whitegate","jabatan":"KOMDIS","division":"DIREKSI & MANAJEMEN","date":"2026-04-27","shift":"Shift 1","on":"21:00","off":"23:15","seconds":8100,"ts":1777222860000},{"id":"mig2f0d108ee6","staffId":"","name":"Julian xavier","jabatan":"TRAINEE","division":"STAFF MEDIS","date":"2026-04-27","shift":"Shift 1","on":"22:45","off":"23:57","seconds":4320,"ts":1777222860000},{"id":"mig2f0e528d7d","staffId":"","name":"LEON DACOSTA","jabatan":"TRAINEE","division":"STAFF MEDIS","date":"2026-04-27","shift":"Shift 1","on":"00:01","off":"01:42","seconds":6060,"ts":1777222860000},{"id":"mig2f0f8b21fb","staffId":"","name":"LEON DACOSTA","jabatan":"TRAINEE","division":"STAFF MEDIS","date":"2026-04-27","shift":"Shift 2","on":"23:24","off":"23:55","seconds":1860,"ts":1777222920000},{"id":"mig2f1085ab56","staffId":"","name":"Viktor Moriarty","jabatan":"TRAINEE","division":"STAFF MEDIS","date":"2026-04-27","shift":"Shift 1","on":"06:54","off":"14:00","seconds":25560,"ts":1777222860000},{"id":"mig2f119f4ad4","staffId":"","name":"Viktor Moriarty","jabatan":"TRAINEE","division":"STAFF MEDIS","date":"2026-04-27","shift":"Shift 2","on":"15:07","off":"17:30","seconds":8580,"ts":1777222920000},{"id":"mig2f126926d7","staffId":"","name":"Viktor Moriarty","jabatan":"TRAINEE","division":"STAFF MEDIS","date":"2026-04-27","shift":"Shift 3","on":"18:52","off":"19:43","seconds":3060,"ts":1777222980000},{"id":"mig2f13b0f7ff","staffId":"","name":"Armel Quantum","jabatan":"TRAINEE","division":"STAFF MEDIS","date":"2026-04-28","shift":"Shift 1","on":"13:50","off":"16:50","seconds":10800,"ts":1777309260000},{"id":"mig2f148e6546","staffId":"","name":"Armel Quantum","jabatan":"TRAINEE","division":"STAFF MEDIS","date":"2026-04-28","shift":"Shift 2","on":"18:40","off":"22:20","seconds":13200,"ts":1777309320000},{"id":"mig2f155eec60","staffId":"","name":"Draco Hidayat Hawkins","jabatan":"SEKBEN","division":"DIREKSI & MANAJEMEN","date":"2026-04-28","shift":"Shift 1","on":"21:27","off":"23:19","seconds":6720,"ts":1777309260000},{"id":"mig2f16fc10a8","staffId":"","name":"Grizelle D Whitegate","jabatan":"KOMDIS","division":"DIREKSI & MANAJEMEN","date":"2026-04-28","shift":"Shift 1","on":"20:25","off":"22:20","seconds":6900,"ts":1777309260000},{"id":"mig2f17ec8440","staffId":"","name":"Julian xavier","jabatan":"TRAINEE","division":"STAFF MEDIS","date":"2026-04-28","shift":"Shift 1","on":"16:34","off":"17:58","seconds":5040,"ts":1777309260000},{"id":"mig2f189a432e","staffId":"","name":"Julian xavier","jabatan":"TRAINEE","division":"STAFF MEDIS","date":"2026-04-28","shift":"Shift 2","on":"23:57","off":"23:59","seconds":120,"ts":1777309320000},{"id":"mig2f19fb541c","staffId":"","name":"LEON DACOSTA","jabatan":"TRAINEE","division":"STAFF MEDIS","date":"2026-04-28","shift":"Shift 1","on":"20:18","off":"23:59","seconds":13260,"ts":1777309260000},{"id":"mig2f1a19fb01","staffId":"","name":"Viktor Moriarty","jabatan":"TRAINEE","division":"STAFF MEDIS","date":"2026-04-28","shift":"Shift 1","on":"08:15","off":"14:00","seconds":20700,"ts":1777309260000},{"id":"mig2f1bfd842b","staffId":"","name":"Armel Quantum","jabatan":"TRAINEE","division":"STAFF MEDIS","date":"2026-04-29","shift":"Shift 1","on":"14:20","off":"17:00","seconds":9600,"ts":1777395660000},{"id":"mig2f1cd3c501","staffId":"","name":"Armel Quantum","jabatan":"TRAINEE","division":"STAFF MEDIS","date":"2026-04-29","shift":"Shift 2","on":"19:00","off":"22:20","seconds":12000,"ts":1777395720000},{"id":"mig2f1dcf0928","staffId":"","name":"Carellia Jianyx Whitegate","jabatan":"TRAINEE","division":"STAFF MEDIS","date":"2026-04-29","shift":"Shift 1","on":"15:34","off":"17:05","seconds":5460,"ts":1777395660000},{"id":"mig2f1eb4c4e9","staffId":"","name":"Carellia Jianyx Whitegate","jabatan":"TRAINEE","division":"STAFF MEDIS","date":"2026-04-29","shift":"Shift 2","on":"20:53","off":"23:59","seconds":11160,"ts":1777395720000},{"id":"mig2f1fd42339","staffId":"","name":"Draco Hidayat Hawkins","jabatan":"SEKBEN","division":"DIREKSI & MANAJEMEN","date":"2026-04-29","shift":"Shift 1","on":"22:37","off":"23:59","seconds":4920,"ts":1777395660000},{"id":"mig2f2001b80a","staffId":"","name":"Ellena Snorris","jabatan":"DOKTER SPESIALIS","division":"STAFF MEDIS","date":"2026-04-29","shift":"Shift 1","on":"23:09","off":"23:59","seconds":3000,"ts":1777395660000},{"id":"mig2f21a76f73","staffId":"","name":"Grizelle D Whitegate","jabatan":"KOMDIS","division":"DIREKSI & MANAJEMEN","date":"2026-04-29","shift":"Shift 1","on":"21:00","off":"23:45","seconds":9900,"ts":1777395660000},{"id":"mig2f22bc8b0d","staffId":"","name":"Julian xavier","jabatan":"TRAINEE","division":"STAFF MEDIS","date":"2026-04-29","shift":"Shift 1","on":"00:00","off":"01:00","seconds":3600,"ts":1777395660000},{"id":"mig2f23336d9e","staffId":"","name":"Julian xavier","jabatan":"TRAINEE","division":"STAFF MEDIS","date":"2026-04-29","shift":"Shift 2","on":"21:34","off":"23:59","seconds":8700,"ts":1777395720000},{"id":"mig2f24a037cf","staffId":"","name":"LEON DACOSTA","jabatan":"TRAINEE","division":"STAFF MEDIS","date":"2026-04-29","shift":"Shift 1","on":"00:01","off":"00:05","seconds":240,"ts":1777395660000},{"id":"mig2f259c49b5","staffId":"","name":"LEON DACOSTA","jabatan":"TRAINEE","division":"STAFF MEDIS","date":"2026-04-29","shift":"Shift 2","on":"21:24","off":"23:59","seconds":9300,"ts":1777395720000},{"id":"mig2f266ff1a9","staffId":"","name":"Viktor Moriarty","jabatan":"TRAINEE","division":"STAFF MEDIS","date":"2026-04-29","shift":"Shift 1","on":"09:44","off":"14:10","seconds":15960,"ts":1777395660000},{"id":"mig2f274e925a","staffId":"","name":"luxii de voltre","jabatan":"TRAINEE","division":"STAFF MEDIS","date":"2026-04-29","shift":"Shift 1","on":"16:00","off":"17:05","seconds":3900,"ts":1777395660000},{"id":"mig2f28564390","staffId":"","name":"Armel Quantum","jabatan":"TRAINEE","division":"STAFF MEDIS","date":"2026-04-30","shift":"Shift 1","on":"15:20","off":"17:00","seconds":6000,"ts":1777482060000},{"id":"mig2f299d9014","staffId":"","name":"Armel Quantum","jabatan":"TRAINEE","division":"STAFF MEDIS","date":"2026-04-30","shift":"Shift 2","on":"22:00","off":"23:20","seconds":4800,"ts":1777482120000},{"id":"mig2f2a5cb460","staffId":"","name":"Carellia Jianyx Whitegate","jabatan":"TRAINEE","division":"STAFF MEDIS","date":"2026-04-30","shift":"Shift 1","on":"00:00","off":"00:20","seconds":1200,"ts":1777482060000},{"id":"mig2f2b6e194d","staffId":"","name":"Carellia Jianyx Whitegate","jabatan":"TRAINEE","division":"STAFF MEDIS","date":"2026-04-30","shift":"Shift 2","on":"20:44","off":"21:10","seconds":1560,"ts":1777482120000},{"id":"mig2f2c48920b","staffId":"","name":"Carellia Jianyx Whitegate","jabatan":"TRAINEE","division":"STAFF MEDIS","date":"2026-04-30","shift":"Shift 3","on":"21:55","off":"23:59","seconds":7440,"ts":1777482180000},{"id":"mig2f2d88327f","staffId":"","name":"Draco Hidayat Hawkins","jabatan":"SEKBEN","division":"DIREKSI & MANAJEMEN","date":"2026-04-30","shift":"Shift 1","on":"00:01","off":"01:41","seconds":6000,"ts":1777482060000},{"id":"mig2f2e787d21","staffId":"","name":"Ellena Snorris","jabatan":"DOKTER SPESIALIS","division":"STAFF MEDIS","date":"2026-04-30","shift":"Shift 1","on":"20:56","off":"23:59","seconds":10980,"ts":1777482060000},{"id":"mig2f2f3072c5","staffId":"","name":"Julian xavier","jabatan":"TRAINEE","division":"STAFF MEDIS","date":"2026-04-30","shift":"Shift 1","on":"00:00","off":"01:00","seconds":3600,"ts":1777482060000},{"id":"mig2f30482f7f","staffId":"","name":"Julian xavier","jabatan":"TRAINEE","division":"STAFF MEDIS","date":"2026-04-30","shift":"Shift 2","on":"22:00","off":"23:59","seconds":7140,"ts":1777482120000},{"id":"mig2f318dc4c1","staffId":"","name":"LEON DACOSTA","jabatan":"TRAINEE","division":"STAFF MEDIS","date":"2026-04-30","shift":"Shift 1","on":"00:01","off":"00:05","seconds":240,"ts":1777482060000},{"id":"mig2f32c7a099","staffId":"","name":"LEON DACOSTA","jabatan":"TRAINEE","division":"STAFF MEDIS","date":"2026-04-30","shift":"Shift 2","on":"21:51","off":"23:59","seconds":7680,"ts":1777482120000},{"id":"mig2f3360d1a0","staffId":"","name":"Armel Quantum","jabatan":"TRAINEE","division":"STAFF MEDIS","date":"2026-05-01","shift":"Shift 1","on":"14:00","off":"16:00","seconds":7200,"ts":1777568460000},{"id":"mig2f346c8984","staffId":"","name":"Armel Quantum","jabatan":"TRAINEE","division":"STAFF MEDIS","date":"2026-05-01","shift":"Shift 2","on":"19:59","off":"23:59","seconds":14400,"ts":1777568520000},{"id":"mig2f356029e3","staffId":"","name":"Carellia Jianyx Whitegate","jabatan":"DOKTER UMUM","division":"STAFF MEDIS","date":"2026-05-01","shift":"Shift 1","on":"00:00","off":"00:54","seconds":3240,"ts":1777568460000},{"id":"mig2f36d8f84c","staffId":"","name":"Carellia Jianyx Whitegate","jabatan":"DOKTER UMUM","division":"STAFF MEDIS","date":"2026-05-01","shift":"Shift 2","on":"20:45","off":"23:59","seconds":11640,"ts":1777568520000},{"id":"mig2f37e41c3c","staffId":"","name":"Draco Hidayat Hawkins","jabatan":"SEKBEN","division":"DIREKSI & MANAJEMEN","date":"2026-05-01","shift":"Shift 1","on":"20:16","off":"23:59","seconds":13380,"ts":1777568460000},{"id":"mig2f38eadd61","staffId":"","name":"Dyvetta O. Kratawijaya","jabatan":"TRAINEE","division":"STAFF MEDIS","date":"2026-05-01","shift":"Shift 1","on":"20:30","off":"23:00","seconds":9000,"ts":1777568460000},{"id":"mig2f391a91d5","staffId":"","name":"Ellena Snorris","jabatan":"SEKBEN","division":"DIREKSI & MANAJEMEN","date":"2026-05-01","shift":"Shift 1","on":"20:26","off":"23:59","seconds":12780,"ts":1777568460000},{"id":"mig2f3a2c358c","staffId":"","name":"Grizelle D Whitegate","jabatan":"KOMDIS","division":"DIREKSI & MANAJEMEN","date":"2026-05-01","shift":"Shift 1","on":"20:20","off":"23:59","seconds":13140,"ts":1777568460000},{"id":"mig2f3b32912d","staffId":"","name":"Julian xavier","jabatan":"TRAINEE","division":"STAFF MEDIS","date":"2026-05-01","shift":"Shift 1","on":"21:06","off":"23:59","seconds":10380,"ts":1777568460000},{"id":"mig2f3cffc886","staffId":"","name":"LEON DACOSTA","jabatan":"DOKTER UMUM","division":"STAFF MEDIS","date":"2026-05-01","shift":"Shift 1","on":"00:01","off":"00:54","seconds":3180,"ts":1777568460000},{"id":"mig2f3d388b90","staffId":"","name":"Noah Esvander","jabatan":"TRAINEE","division":"STAFF MEDIS","date":"2026-05-01","shift":"Shift 1","on":"20:59","off":"23:59","seconds":10800,"ts":1777568460000},{"id":"mig2f3e89c3c2","staffId":"","name":"VANDERWOODSEN JACK BLITZ","jabatan":"TRAINEE","division":"STAFF MEDIS","date":"2026-05-01","shift":"Shift 1","on":"15:00","off":"17:00","seconds":7200,"ts":1777568460000},{"id":"mig2f3feb9d64","staffId":"","name":"VANDERWOODSEN JACK BLITZ","jabatan":"TRAINEE","division":"STAFF MEDIS","date":"2026-05-01","shift":"Shift 2","on":"19:32","off":"23:04","seconds":12720,"ts":1777568520000},{"id":"mig2f4050f9ea","staffId":"","name":"Viktor Moriarty","jabatan":"TRAINEE","division":"STAFF MEDIS","date":"2026-05-01","shift":"Shift 1","on":"10:49","off":"17:30","seconds":24060,"ts":1777568460000},{"id":"mig2f41024804","staffId":"","name":"Viktor Moriarty","jabatan":"TRAINEE","division":"STAFF MEDIS","date":"2026-05-01","shift":"Shift 2","on":"19:20","off":"19:38","seconds":1080,"ts":1777568520000},{"id":"mig2f42b0c462","staffId":"","name":"Viktor Moriarty","jabatan":"TRAINEE","division":"STAFF MEDIS","date":"2026-05-01","shift":"Shift 3","on":"19:50","off":"20:30","seconds":2400,"ts":1777568580000},{"id":"mig2f43ad590b","staffId":"","name":"luxii de voltre","jabatan":"TRAINEE","division":"STAFF MEDIS","date":"2026-05-01","shift":"Shift 1","on":"20:50","off":"23:40","seconds":10200,"ts":1777568460000},{"id":"mig2f445a992d","staffId":"","name":"Armel Quantum","jabatan":"TRAINEE","division":"STAFF MEDIS","date":"2026-05-02","shift":"Shift 1","on":"13:19","off":"17:19","seconds":14400,"ts":1777654860000},{"id":"mig2f4509454f","staffId":"","name":"Armel Quantum","jabatan":"TRAINEE","division":"STAFF MEDIS","date":"2026-05-02","shift":"Shift 2","on":"18:16","off":"22:16","seconds":14400,"ts":1777654920000},{"id":"mig2f46800a47","staffId":"","name":"Carellia Jianyx Whitegate","jabatan":"DOKTER UMUM","division":"STAFF MEDIS","date":"2026-05-02","shift":"Shift 1","on":"00:00","off":"00:19","seconds":1140,"ts":1777654860000},{"id":"mig2f47820b21","staffId":"","name":"Carellia Jianyx Whitegate","jabatan":"DOKTER UMUM","division":"STAFF MEDIS","date":"2026-05-02","shift":"Shift 2","on":"21:23","off":"22:25","seconds":3720,"ts":1777654920000},{"id":"mig2f48a53161","staffId":"","name":"Draco Hidayat Hawkins","jabatan":"SEKBEN","division":"DIREKSI & MANAJEMEN","date":"2026-05-02","shift":"Shift 1","on":"00:01","off":"01:30","seconds":5340,"ts":1777654860000},{"id":"mig2f49126c49","staffId":"","name":"Draco Hidayat Hawkins","jabatan":"SEKBEN","division":"DIREKSI & MANAJEMEN","date":"2026-05-02","shift":"Shift 2","on":"21:36","off":"23:59","seconds":8580,"ts":1777654920000},{"id":"mig2f4acdbcb3","staffId":"","name":"Dyvetta O. Kratawijaya","jabatan":"TRAINEE","division":"STAFF MEDIS","date":"2026-05-02","shift":"Shift 1","on":"19:50","off":"21:10","seconds":4800,"ts":1777654860000},{"id":"mig2f4bae4a1a","staffId":"","name":"Grizelle D Whitegate","jabatan":"KOMDIS","division":"DIREKSI & MANAJEMEN","date":"2026-05-02","shift":"Shift 1","on":"00:00","off":"00:15","seconds":900,"ts":1777654860000},{"id":"mig2f4ca4577e","staffId":"","name":"Julian xavier","jabatan":"TRAINEE","division":"STAFF MEDIS","date":"2026-05-02","shift":"Shift 1","on":"00:01","off":"00:23","seconds":1320,"ts":1777654860000},{"id":"mig2f4d7bcde4","staffId":"","name":"Julian xavier","jabatan":"TRAINEE","division":"STAFF MEDIS","date":"2026-05-02","shift":"Shift 2","on":"14:23","off":"15:35","seconds":4320,"ts":1777654920000},{"id":"mig2f4e89d58c","staffId":"","name":"Noah Esvander","jabatan":"TRAINEE","division":"STAFF MEDIS","date":"2026-05-02","shift":"Shift 1","on":"00:00","off":"00:22","seconds":1320,"ts":1777654860000},{"id":"mig2f4f15c43f","staffId":"","name":"VANDERWOODSEN JACK BLITZ","jabatan":"TRAINEE","division":"STAFF MEDIS","date":"2026-05-02","shift":"Shift 1","on":"13:35","off":"17:23","seconds":13680,"ts":1777654860000},{"id":"mig2f506a26a8","staffId":"","name":"VANDERWOODSEN JACK BLITZ","jabatan":"TRAINEE","division":"STAFF MEDIS","date":"2026-05-02","shift":"Shift 2","on":"20:00","off":"21:56","seconds":6960,"ts":1777654920000},{"id":"mig2f5170df1e","staffId":"","name":"Viktor Moriarty","jabatan":"TRAINEE","division":"STAFF MEDIS","date":"2026-05-02","shift":"Shift 1","on":"00:30","off":"01:30","seconds":3600,"ts":1777654860000},{"id":"mig2f52ec419b","staffId":"","name":"Viktor Moriarty","jabatan":"TRAINEE","division":"STAFF MEDIS","date":"2026-05-02","shift":"Shift 2","on":"08:50","off":"17:30","seconds":31200,"ts":1777654920000},{"id":"mig2f53e5a453","staffId":"","name":"luxii de voltre","jabatan":"TRAINEE","division":"STAFF MEDIS","date":"2026-05-02","shift":"Shift 1","on":"07:50","off":"10:18","seconds":8880,"ts":1777654860000},{"id":"mig2f54b47436","staffId":"","name":"Armel Quantum","jabatan":"TRAINEE","division":"STAFF MEDIS","date":"2026-05-03","shift":"Shift 1","on":"14:00","off":"17:00","seconds":10800,"ts":1777741260000},{"id":"mig2f559273ee","staffId":"","name":"Armel Quantum","jabatan":"TRAINEE","division":"STAFF MEDIS","date":"2026-05-03","shift":"Shift 2","on":"19:00","off":"22:00","seconds":10800,"ts":1777741320000},{"id":"mig2f5605f599","staffId":"","name":"Draco Hidayat Hawkins","jabatan":"SEKBEN","division":"DIREKSI & MANAJEMEN","date":"2026-05-03","shift":"Shift 1","on":"00:01","off":"00:30","seconds":1740,"ts":1777741260000},{"id":"mig2f57309d04","staffId":"","name":"Draco Hidayat Hawkins","jabatan":"SEKBEN","division":"DIREKSI & MANAJEMEN","date":"2026-05-03","shift":"Shift 2","on":"22:16","off":"23:59","seconds":6180,"ts":1777741320000},{"id":"mig2f58d28203","staffId":"","name":"Dyvetta O. Kratawijaya","jabatan":"TRAINEE","division":"STAFF MEDIS","date":"2026-05-03","shift":"Shift 1","on":"14:30","off":"16:20","seconds":6600,"ts":1777741260000},{"id":"mig2f5986d9e2","staffId":"","name":"Ellena Snorris","jabatan":"SEKBEN","division":"DIREKSI & MANAJEMEN","date":"2026-05-03","shift":"Shift 1","on":"22:49","off":"23:59","seconds":4200,"ts":1777741260000},{"id":"mig2f5a2f5b7d","staffId":"","name":"Grizelle D Whitegate","jabatan":"KOMDIS","division":"DIREKSI & MANAJEMEN","date":"2026-05-03","shift":"Shift 1","on":"20:40","off":"23:59","seconds":11940,"ts":1777741260000},{"id":"mig2f5bf07271","staffId":"","name":"Julian xavier","jabatan":"TRAINEE","division":"STAFF MEDIS","date":"2026-05-03","shift":"Shift 1","on":"20:20","off":"22:35","seconds":8100,"ts":1777741260000},{"id":"mig2f5cba616e","staffId":"","name":"VANDERWOODSEN JACK BLITZ","jabatan":"TRAINEE","division":"STAFF MEDIS","date":"2026-05-03","shift":"Shift 1","on":"16:39","off":"17:12","seconds":1980,"ts":1777741260000},{"id":"mig2f5d09809e","staffId":"","name":"VANDERWOODSEN JACK BLITZ","jabatan":"TRAINEE","division":"STAFF MEDIS","date":"2026-05-03","shift":"Shift 2","on":"18:43","off":"22:30","seconds":13620,"ts":1777741320000}],"archivedAt":1777827540000},{"key":"2026-05-04","start":"2026-05-04","end":"2026-05-10","records":[{"id":"mig2f5e24802a","staffId":"","name":"Armel Quantum","jabatan":"TRAINEE","division":"STAFF MEDIS","date":"2026-05-04","shift":"Shift 1","on":"16:35","off":"17:25","seconds":3000,"ts":1777827660000},{"id":"mig2f5f795886","staffId":"","name":"Armel Quantum","jabatan":"TRAINEE","division":"STAFF MEDIS","date":"2026-05-04","shift":"Shift 2","on":"18:56","off":"23:39","seconds":16980,"ts":1777827720000},{"id":"mig2f6025b130","staffId":"","name":"Carellia Jianyx Whitegate","jabatan":"DOKTER UMUM","division":"STAFF MEDIS","date":"2026-05-04","shift":"Shift 1","on":"20:39","off":"22:26","seconds":6420,"ts":1777827660000},{"id":"mig2f6110143d","staffId":"","name":"Draco Hidayat Hawkins","jabatan":"SEKBEN","division":"DIREKSI & MANAJEMEN","date":"2026-05-04","shift":"Shift 1","on":"00:01","off":"02:20","seconds":8340,"ts":1777827660000},{"id":"mig2f6241ad41","staffId":"","name":"Draco Hidayat Hawkins","jabatan":"SEKBEN","division":"DIREKSI & MANAJEMEN","date":"2026-05-04","shift":"Shift 2","on":"21:46","off":"23:59","seconds":7980,"ts":1777827720000},{"id":"mig2f63c10601","staffId":"","name":"Fae Bellen","jabatan":"HRD","division":"DIREKSI & MANAJEMEN","date":"2026-05-04","shift":"Shift 1","on":"14:30","off":"17:32","seconds":10920,"ts":1777827660000},{"id":"mig2f64cc3461","staffId":"","name":"Fae Bellen","jabatan":"HRD","division":"DIREKSI & MANAJEMEN","date":"2026-05-04","shift":"Shift 2","on":"18:54","off":"22:30","seconds":12960,"ts":1777827720000},{"id":"mig2f65f03406","staffId":"","name":"Grizelle D Whitegate","jabatan":"KOMDIS","division":"DIREKSI & MANAJEMEN","date":"2026-05-04","shift":"Shift 1","on":"00:00","off":"01:55","seconds":6900,"ts":1777827660000},{"id":"mig2f66b4c2a0","staffId":"","name":"Grizelle D Whitegate","jabatan":"KOMDIS","division":"DIREKSI & MANAJEMEN","date":"2026-05-04","shift":"Shift 2","on":"20:40","off":"23:59","seconds":11940,"ts":1777827720000},{"id":"mig2f67b954ca","staffId":"","name":"Julian xavier","jabatan":"TRAINEE","division":"STAFF MEDIS","date":"2026-05-04","shift":"Shift 1","on":"13:12","off":"17:23","seconds":15060,"ts":1777827660000},{"id":"mig2f68faddc3","staffId":"","name":"Julian xavier","jabatan":"TRAINEE","division":"STAFF MEDIS","date":"2026-05-04","shift":"Shift 2","on":"20:33","off":"23:51","seconds":11880,"ts":1777827720000},{"id":"mig2f692c4a08","staffId":"","name":"Armel Quantum","jabatan":"TRAINEE","division":"STAFF MEDIS","date":"2026-05-05","shift":"Shift 1","on":"20:00","off":"22:27","seconds":8820,"ts":1777914060000},{"id":"mig2f6aeedf68","staffId":"","name":"Carellia Jianyx Whitegate","jabatan":"DOKTER UMUM","division":"STAFF MEDIS","date":"2026-05-05","shift":"Shift 1","on":"20:09","off":"21:25","seconds":4560,"ts":1777914060000},{"id":"mig2f6b8341ee","staffId":"","name":"Draco Hidayat Hawkins","jabatan":"SEKBEN","division":"DIREKSI & MANAJEMEN","date":"2026-05-05","shift":"Shift 1","on":"00:01","off":"00:21","seconds":1200,"ts":1777914060000},{"id":"mig2f6c8b71c4","staffId":"","name":"Draco Hidayat Hawkins","jabatan":"SEKBEN","division":"DIREKSI & MANAJEMEN","date":"2026-05-05","shift":"Shift 2","on":"22:46","off":"23:56","seconds":4200,"ts":1777914120000},{"id":"mig2f6d9d1848","staffId":"","name":"Dyvetta O. Kratawijaya","jabatan":"TRAINEE","division":"STAFF MEDIS","date":"2026-05-05","shift":"Shift 1","on":"20:25","off":"22:30","seconds":7500,"ts":1777914060000},{"id":"mig2f6e87b875","staffId":"","name":"Fae Bellen","jabatan":"HRD","division":"DIREKSI & MANAJEMEN","date":"2026-05-05","shift":"Shift 1","on":"13:28","off":"14:45","seconds":4620,"ts":1777914060000},{"id":"mig2f6f304b3b","staffId":"","name":"Grizelle D Whitegate","jabatan":"KOMDIS","division":"DIREKSI & MANAJEMEN","date":"2026-05-05","shift":"Shift 1","on":"00:00","off":"04:22","seconds":15720,"ts":1777914060000},{"id":"mig2f704166bf","staffId":"","name":"Grizelle D Whitegate","jabatan":"KOMDIS","division":"DIREKSI & MANAJEMEN","date":"2026-05-05","shift":"Shift 2","on":"16:32","off":"17:27","seconds":3300,"ts":1777914120000},{"id":"mig2f712fd91d","staffId":"","name":"Grizelle D Whitegate","jabatan":"KOMDIS","division":"DIREKSI & MANAJEMEN","date":"2026-05-05","shift":"Shift 3","on":"19:55","off":"22:09","seconds":8040,"ts":1777914180000},{"id":"mig2f725bc679","staffId":"","name":"Julian xavier","jabatan":"TRAINEE","division":"STAFF MEDIS","date":"2026-05-05","shift":"Shift 1","on":"22:12","off":"23:59","seconds":6420,"ts":1777914060000},{"id":"mig2f7346a875","staffId":"","name":"Armel Quantum","jabatan":"TRAINEE","division":"STAFF MEDIS","date":"2026-05-06","shift":"Shift 1","on":"16:11","off":"17:11","seconds":3600,"ts":1778000460000},{"id":"mig2f744167ae","staffId":"","name":"Armel Quantum","jabatan":"TRAINEE","division":"STAFF MEDIS","date":"2026-05-06","shift":"Shift 2","on":"18:48","off":"23:28","seconds":16800,"ts":1778000520000},{"id":"mig2f75384c92","staffId":"","name":"Carellia Jianyx Whitegate","jabatan":"DOKTER UMUM","division":"STAFF MEDIS","date":"2026-05-06","shift":"Shift 1","on":"21:10","off":"22:24","seconds":4440,"ts":1778000460000},{"id":"mig2f76667cae","staffId":"","name":"Carellia Jianyx Whitegate","jabatan":"DOKTER UMUM","division":"STAFF MEDIS","date":"2026-05-06","shift":"Shift 2","on":"23:01","off":"23:26","seconds":1500,"ts":1778000520000},{"id":"mig2f77a5f996","staffId":"","name":"Draco Hidayat Hawkins","jabatan":"SEKBEN","division":"DIREKSI & MANAJEMEN","date":"2026-05-06","shift":"Shift 1","on":"21:26","off":"23:59","seconds":9180,"ts":1778000460000},{"id":"mig2f784c323d","staffId":"","name":"Dyvetta O. Kratawijaya","jabatan":"TRAINEE","division":"STAFF MEDIS","date":"2026-05-06","shift":"Shift 1","on":"19:58","off":"23:50","seconds":13920,"ts":1778000460000},{"id":"mig2f79f79324","staffId":"","name":"Ellena Snorris","jabatan":"SEKBEN","division":"DIREKSI & MANAJEMEN","date":"2026-05-06","shift":"Shift 1","on":"22:26","off":"23:33","seconds":4020,"ts":1778000460000},{"id":"mig2f7adb9dd8","staffId":"","name":"Fae Bellen","jabatan":"HRD","division":"DIREKSI & MANAJEMEN","date":"2026-05-06","shift":"Shift 1","on":"18:40","off":"22:44","seconds":14640,"ts":1778000460000},{"id":"mig2f7bc49e8b","staffId":"","name":"Grizelle D Whitegate","jabatan":"KOMDIS","division":"DIREKSI & MANAJEMEN","date":"2026-05-06","shift":"Shift 1","on":"03:16","off":"05:17","seconds":7260,"ts":1778000460000},{"id":"mig2f7c8d1b9d","staffId":"","name":"Grizelle D Whitegate","jabatan":"KOMDIS","division":"DIREKSI & MANAJEMEN","date":"2026-05-06","shift":"Shift 2","on":"20:35","off":"23:59","seconds":12240,"ts":1778000520000},{"id":"mig2f7d3e836e","staffId":"","name":"Julian xavier","jabatan":"TRAINEE","division":"STAFF MEDIS","date":"2026-05-06","shift":"Shift 1","on":"00:01","off":"00:57","seconds":3360,"ts":1778000460000},{"id":"mig2f7e2c1dc8","staffId":"","name":"Julian xavier","jabatan":"TRAINEE","division":"STAFF MEDIS","date":"2026-05-06","shift":"Shift 2","on":"22:55","off":"23:59","seconds":3840,"ts":1778000520000},{"id":"mig2f7f120bc3","staffId":"","name":"VANDERWOODSEN JACK BLITZ","jabatan":"TRAINEE","division":"STAFF MEDIS","date":"2026-05-06","shift":"Shift 1","on":"08:00","off":"16:02","seconds":28920,"ts":1778000460000},{"id":"mig2f80f2257e","staffId":"","name":"VANDERWOODSEN JACK BLITZ","jabatan":"TRAINEE","division":"STAFF MEDIS","date":"2026-05-06","shift":"Shift 2","on":"21:00","off":"22:30","seconds":5400,"ts":1778000520000},{"id":"mig2f811019e7","staffId":"","name":"Armel Quantum","jabatan":"TRAINEE","division":"STAFF MEDIS","date":"2026-05-07","shift":"Shift 1","on":"21:19","off":"23:19","seconds":7200,"ts":1778086860000},{"id":"mig2f82452a1d","staffId":"","name":"Carellia Jianyx Whitegate","jabatan":"DOKTER UMUM","division":"STAFF MEDIS","date":"2026-05-07","shift":"Shift 1","on":"20:47","off":"22:39","seconds":6720,"ts":1778086860000},{"id":"mig2f83b49f9e","staffId":"","name":"Carellia Jianyx Whitegate","jabatan":"DOKTER UMUM","division":"STAFF MEDIS","date":"2026-05-07","shift":"Shift 2","on":"23:01","off":"23:59","seconds":3480,"ts":1778086920000},{"id":"mig2f8477492c","staffId":"","name":"Draco Hidayat Hawkins","jabatan":"SEKBEN","division":"DIREKSI & MANAJEMEN","date":"2026-05-07","shift":"Shift 1","on":"00:01","off":"02:11","seconds":7800,"ts":1778086860000},{"id":"mig2f85e4d2f1","staffId":"","name":"Draco Hidayat Hawkins","jabatan":"SEKBEN","division":"DIREKSI & MANAJEMEN","date":"2026-05-07","shift":"Shift 2","on":"21:26","off":"23:59","seconds":9180,"ts":1778086920000},{"id":"mig2f86aa783d","staffId":"","name":"Dyvetta O. Kratawijaya","jabatan":"TRAINEE","division":"STAFF MEDIS","date":"2026-05-07","shift":"Shift 1","on":"19:28","off":"21:30","seconds":7320,"ts":1778086860000},{"id":"mig2f87d2d09e","staffId":"","name":"Ellena Snorris","jabatan":"SEKBEN","division":"DIREKSI & MANAJEMEN","date":"2026-05-07","shift":"Shift 1","on":"22:35","off":"23:59","seconds":5040,"ts":1778086860000},{"id":"mig2f88b4c7a7","staffId":"","name":"Fae Bellen","jabatan":"HRD","division":"DIREKSI & MANAJEMEN","date":"2026-05-07","shift":"Shift 1","on":"18:10","off":"21:14","seconds":11040,"ts":1778086860000},{"id":"mig2f890dae1f","staffId":"","name":"Grizelle D Whitegate","jabatan":"KOMDIS","division":"DIREKSI & MANAJEMEN","date":"2026-05-07","shift":"Shift 1","on":"00:00","off":"00:20","seconds":1200,"ts":1778086860000},{"id":"mig2f8a9617a8","staffId":"","name":"Grizelle D Whitegate","jabatan":"KOMDIS","division":"DIREKSI & MANAJEMEN","date":"2026-05-07","shift":"Shift 2","on":"20:35","off":"23:59","seconds":12240,"ts":1778086920000},{"id":"mig2f8bb152c5","staffId":"","name":"Julian xavier","jabatan":"TRAINEE","division":"STAFF MEDIS","date":"2026-05-07","shift":"Shift 1","on":"00:01","off":"01:23","seconds":4920,"ts":1778086860000},{"id":"mig2f8cc5e4ba","staffId":"","name":"Julian xavier","jabatan":"TRAINEE","division":"STAFF MEDIS","date":"2026-05-07","shift":"Shift 2","on":"21:30","off":"23:40","seconds":7800,"ts":1778086920000},{"id":"mig2f8da94ac8","staffId":"","name":"LEON DACOSTA","jabatan":"DOKTER UMUM","division":"STAFF MEDIS","date":"2026-05-07","shift":"Shift 1","on":"22:58","off":"23:59","seconds":3660,"ts":1778086860000},{"id":"mig2f8efab32d","staffId":"","name":"VANDERWOODSEN JACK BLITZ","jabatan":"TRAINEE","division":"STAFF MEDIS","date":"2026-05-07","shift":"Shift 1","on":"14:45","off":"16:00","seconds":4500,"ts":1778086860000},{"id":"mig2f8f46254c","staffId":"","name":"VANDERWOODSEN JACK BLITZ","jabatan":"TRAINEE","division":"STAFF MEDIS","date":"2026-05-07","shift":"Shift 2","on":"19:43","off":"23:45","seconds":14520,"ts":1778086920000},{"id":"mig2f908161b9","staffId":"","name":"Armel Quantum","jabatan":"TRAINEE","division":"STAFF MEDIS","date":"2026-05-08","shift":"Shift 1","on":"20:18","off":"23:59","seconds":13260,"ts":1778173260000},{"id":"mig2f9186a95d","staffId":"","name":"Carellia Jianyx Whitegate","jabatan":"DOKTER UMUM","division":"STAFF MEDIS","date":"2026-05-08","shift":"Shift 1","on":"00:00","off":"01:50","seconds":6600,"ts":1778173260000},{"id":"mig2f9214ad16","staffId":"","name":"Carellia Jianyx Whitegate","jabatan":"DOKTER UMUM","division":"STAFF MEDIS","date":"2026-05-08","shift":"Shift 2","on":"20:17","off":"23:03","seconds":9960,"ts":1778173320000},{"id":"mig2f93b7deae","staffId":"","name":"Draco Hidayat Hawkins","jabatan":"SEKBEN","division":"DIREKSI & MANAJEMEN","date":"2026-05-08","shift":"Shift 1","on":"00:01","off":"00:41","seconds":2400,"ts":1778173260000},{"id":"mig2f9419786b","staffId":"","name":"Draco Hidayat Hawkins","jabatan":"SEKBEN","division":"DIREKSI & MANAJEMEN","date":"2026-05-08","shift":"Shift 2","on":"22:36","off":"23:49","seconds":4380,"ts":1778173320000},{"id":"mig2f9538ffc6","staffId":"","name":"Dyvetta O. Kratawijaya","jabatan":"TRAINEE","division":"STAFF MEDIS","date":"2026-05-08","shift":"Shift 1","on":"20:18","off":"23:59","seconds":13260,"ts":1778173260000},{"id":"mig2f96bf841e","staffId":"","name":"Ellena Snorris","jabatan":"SEKBEN","division":"DIREKSI & MANAJEMEN","date":"2026-05-08","shift":"Shift 1","on":"20:32","off":"22:03","seconds":5460,"ts":1778173260000},{"id":"mig2f97f33c7d","staffId":"","name":"Grizelle D Whitegate","jabatan":"KOMDIS","division":"DIREKSI & MANAJEMEN","date":"2026-05-08","shift":"Shift 1","on":"00:00","off":"00:25","seconds":1500,"ts":1778173260000},{"id":"mig2f9878827a","staffId":"","name":"Grizelle D Whitegate","jabatan":"KOMDIS","division":"DIREKSI & MANAJEMEN","date":"2026-05-08","shift":"Shift 2","on":"20:55","off":"23:23","seconds":8880,"ts":1778173320000},{"id":"mig2f991337ef","staffId":"","name":"LEON DACOSTA","jabatan":"DOKTER UMUM","division":"STAFF MEDIS","date":"2026-05-08","shift":"Shift 1","on":"00:01","off":"02:03","seconds":7320,"ts":1778173260000},{"id":"mig2f9aba4974","staffId":"","name":"LEON DACOSTA","jabatan":"DOKTER UMUM","division":"STAFF MEDIS","date":"2026-05-08","shift":"Shift 2","on":"20:15","off":"23:59","seconds":13440,"ts":1778173320000},{"id":"mig2f9b112b8d","staffId":"","name":"Armel Quantum","jabatan":"TRAINEE","division":"STAFF MEDIS","date":"2026-05-09","shift":"Shift 1","on":"00:01","off":"01:07","seconds":3960,"ts":1778259660000},{"id":"mig2f9c36f304","staffId":"","name":"Armel Quantum","jabatan":"TRAINEE","division":"STAFF MEDIS","date":"2026-05-09","shift":"Shift 2","on":"19:28","off":"23:59","seconds":16260,"ts":1778259720000},{"id":"mig2f9d540a7c","staffId":"","name":"Carellia Jianyx Whitegate","jabatan":"DOKTER UMUM","division":"STAFF MEDIS","date":"2026-05-09","shift":"Shift 1","on":"21:13","off":"23:17","seconds":7440,"ts":1778259660000},{"id":"mig2f9e4a0ff9","staffId":"","name":"Draco Hidayat Hawkins","jabatan":"SEKBEN","division":"DIREKSI & MANAJEMEN","date":"2026-05-09","shift":"Shift 1","on":"22:52","off":"23:49","seconds":3420,"ts":1778259660000},{"id":"mig2f9ffee59a","staffId":"","name":"Dyvetta O. Kratawijaya","jabatan":"TRAINEE","division":"STAFF MEDIS","date":"2026-05-09","shift":"Shift 1","on":"00:01","off":"01:10","seconds":4140,"ts":1778259660000},{"id":"mig2fa0352895","staffId":"","name":"Dyvetta O. Kratawijaya","jabatan":"TRAINEE","division":"STAFF MEDIS","date":"2026-05-09","shift":"Shift 2","on":"20:04","off":"23:59","seconds":14100,"ts":1778259720000},{"id":"mig2fa144af1d","staffId":"","name":"Fae Bellen","jabatan":"HRD","division":"DIREKSI & MANAJEMEN","date":"2026-05-09","shift":"Shift 1","on":"00:01","off":"02:00","seconds":7140,"ts":1778259660000},{"id":"mig2fa24261c0","staffId":"","name":"Fae Bellen","jabatan":"HRD","division":"DIREKSI & MANAJEMEN","date":"2026-05-09","shift":"Shift 2","on":"14:35","off":"14:43","seconds":480,"ts":1778259720000},{"id":"mig2fa3378706","staffId":"","name":"Fae Bellen","jabatan":"HRD","division":"DIREKSI & MANAJEMEN","date":"2026-05-09","shift":"Shift 3","on":"21:25","off":"22:24","seconds":3540,"ts":1778259780000},{"id":"mig2fa448e2df","staffId":"","name":"Grizelle D Whitegate","jabatan":"KOMDIS","division":"DIREKSI & MANAJEMEN","date":"2026-05-09","shift":"Shift 1","on":"01:15","off":"05:58","seconds":16980,"ts":1778259660000},{"id":"mig2fa5d316ed","staffId":"","name":"Julian xavier","jabatan":"TRAINEE","division":"STAFF MEDIS","date":"2026-05-09","shift":"Shift 1","on":"20:01","off":"22:57","seconds":10560,"ts":1778259660000},{"id":"mig2fa661937d","staffId":"","name":"LEON DACOSTA","jabatan":"DOKTER UMUM","division":"STAFF MEDIS","date":"2026-05-09","shift":"Shift 1","on":"00:01","off":"01:18","seconds":4620,"ts":1778259660000},{"id":"mig2fa71332a5","staffId":"","name":"Viktor Moriarty","jabatan":"TRAINEE","division":"STAFF MEDIS","date":"2026-05-09","shift":"Shift 1","on":"22:49","off":"23:59","seconds":4200,"ts":1778259660000},{"id":"mig2fa801eb25","staffId":"","name":"Armel Quantum","jabatan":"TRAINEE","division":"STAFF MEDIS","date":"2026-05-10","shift":"Shift 1","on":"19:48","off":"23:30","seconds":13320,"ts":1778346060000},{"id":"mig2fa9fc0955","staffId":"","name":"Carellia Jianyx Whitegate","jabatan":"DOKTER UMUM","division":"STAFF MEDIS","date":"2026-05-10","shift":"Shift 1","on":"21:23","off":"23:28","seconds":7500,"ts":1778346060000},{"id":"mig2faab1a871","staffId":"","name":"Draco Hidayat Hawkins","jabatan":"SEKBEN","division":"DIREKSI & MANAJEMEN","date":"2026-05-10","shift":"Shift 1","on":"21:32","off":"23:29","seconds":7020,"ts":1778346060000},{"id":"mig2fab9f1ce4","staffId":"","name":"Dyvetta O. Kratawijaya","jabatan":"TRAINEE","division":"STAFF MEDIS","date":"2026-05-10","shift":"Shift 1","on":"19:54","off":"23:59","seconds":14700,"ts":1778346060000},{"id":"mig2fac8780f5","staffId":"","name":"Grizelle D Whitegate","jabatan":"KOMDIS","division":"DIREKSI & MANAJEMEN","date":"2026-05-10","shift":"Shift 1","on":"00:38","off":"04:50","seconds":15120,"ts":1778346060000},{"id":"mig2fadc44da5","staffId":"","name":"Grizelle D Whitegate","jabatan":"KOMDIS","division":"DIREKSI & MANAJEMEN","date":"2026-05-10","shift":"Shift 2","on":"05:19","off":"06:00","seconds":2460,"ts":1778346120000},{"id":"mig2fae37abef","staffId":"","name":"Grizelle D Whitegate","jabatan":"KOMDIS","division":"DIREKSI & MANAJEMEN","date":"2026-05-10","shift":"Shift 3","on":"21:33","off":"23:59","seconds":8760,"ts":1778346180000},{"id":"mig2faf4e32c8","staffId":"","name":"Julian xavier","jabatan":"TRAINEE","division":"STAFF MEDIS","date":"2026-05-10","shift":"Shift 1","on":"02:00","off":"03:03","seconds":3780,"ts":1778346060000},{"id":"mig2fb0cd3fba","staffId":"","name":"Julian xavier","jabatan":"TRAINEE","division":"STAFF MEDIS","date":"2026-05-10","shift":"Shift 2","on":"21:00","off":"23:12","seconds":7920,"ts":1778346120000},{"id":"mig2fb181b169","staffId":"","name":"LEON DACOSTA","jabatan":"DOKTER UMUM","division":"STAFF MEDIS","date":"2026-05-10","shift":"Shift 1","on":"20:48","off":"23:59","seconds":11460,"ts":1778346060000},{"id":"mig2fb23d5ac5","staffId":"","name":"Viktor Moriarty","jabatan":"TRAINEE","division":"STAFF MEDIS","date":"2026-05-10","shift":"Shift 1","on":"00:00","off":"01:21","seconds":4860,"ts":1778346060000}],"archivedAt":1778432340000},{"key":"2026-05-11","start":"2026-05-11","end":"2026-05-17","records":[{"id":"mig2fb3152049","staffId":"","name":"Armel Quantum","jabatan":"TRAINEE","division":"STAFF MEDIS","date":"2026-05-11","shift":"Shift 1","on":"15:14","off":"16:34","seconds":4800,"ts":1778432460000},{"id":"mig2fb4818663","staffId":"","name":"Armel Quantum","jabatan":"TRAINEE","division":"STAFF MEDIS","date":"2026-05-11","shift":"Shift 2","on":"19:26","off":"23:26","seconds":14400,"ts":1778432520000},{"id":"mig2fb58d6f26","staffId":"","name":"Carellia Jianyx Whitegate","jabatan":"DOKTER UMUM","division":"STAFF MEDIS","date":"2026-05-11","shift":"Shift 1","on":"20:27","off":"22:17","seconds":6600,"ts":1778432460000},{"id":"mig2fb63b368c","staffId":"","name":"Draco Hidayat Hawkins","jabatan":"SEKBEN","division":"DIREKSI & MANAJEMEN","date":"2026-05-11","shift":"Shift 1","on":"22:52","off":"23:59","seconds":4020,"ts":1778432460000},{"id":"mig2fb74e971d","staffId":"","name":"Dyvetta O. Kratawijaya","jabatan":"TRAINEE","division":"STAFF MEDIS","date":"2026-05-11","shift":"Shift 1","on":"19:32","off":"23:59","seconds":16020,"ts":1778432460000},{"id":"mig2fb8bb2c9f","staffId":"","name":"Ellena Snorris","jabatan":"SEKBEN","division":"DIREKSI & MANAJEMEN","date":"2026-05-11","shift":"Shift 1","on":"20:07","off":"22:46","seconds":9540,"ts":1778432460000},{"id":"mig2fb91badaa","staffId":"","name":"Fae Bellen","jabatan":"HRD","division":"DIREKSI & MANAJEMEN","date":"2026-05-11","shift":"Shift 1","on":"19:20","off":"21:34","seconds":8040,"ts":1778432460000},{"id":"mig2fbaed4315","staffId":"","name":"Grizelle D Whitegate","jabatan":"KOMDIS","division":"DIREKSI & MANAJEMEN","date":"2026-05-11","shift":"Shift 1","on":"00:00","off":"00:05","seconds":300,"ts":1778432460000},{"id":"mig2fbbbf8ec6","staffId":"","name":"Grizelle D Whitegate","jabatan":"KOMDIS","division":"DIREKSI & MANAJEMEN","date":"2026-05-11","shift":"Shift 2","on":"23:01","off":"23:46","seconds":2700,"ts":1778432520000},{"id":"mig2fbc759773","staffId":"","name":"Julian xavier","jabatan":"TRAINEE","division":"STAFF MEDIS","date":"2026-05-11","shift":"Shift 1","on":"21:33","off":"23:01","seconds":5280,"ts":1778432460000},{"id":"mig2fbdda9325","staffId":"","name":"LEON DACOSTA","jabatan":"DOKTER UMUM","division":"STAFF MEDIS","date":"2026-05-11","shift":"Shift 1","on":"00:01","off":"02:40","seconds":9540,"ts":1778432460000},{"id":"mig2fbec6c427","staffId":"","name":"Armel Quantum","jabatan":"TRAINEE","division":"STAFF MEDIS","date":"2026-05-12","shift":"Shift 1","on":"16:35","off":"17:25","seconds":3000,"ts":1778518860000},{"id":"mig2fbf0a522a","staffId":"","name":"Armel Quantum","jabatan":"TRAINEE","division":"STAFF MEDIS","date":"2026-05-12","shift":"Shift 2","on":"18:14","off":"23:06","seconds":17520,"ts":1778518920000},{"id":"mig2fc057d0e0","staffId":"","name":"Carellia Jianyx Whitegate","jabatan":"DOKTER UMUM","division":"STAFF MEDIS","date":"2026-05-12","shift":"Shift 1","on":"20:31","off":"21:43","seconds":4320,"ts":1778518860000},{"id":"mig2fc15bd866","staffId":"","name":"Draco Hidayat Hawkins","jabatan":"SEKBEN","division":"DIREKSI & MANAJEMEN","date":"2026-05-12","shift":"Shift 1","on":"00:01","off":"00:31","seconds":1800,"ts":1778518860000},{"id":"mig2fc29d1a1f","staffId":"","name":"Dyvetta O. Kratawijaya","jabatan":"TRAINEE","division":"STAFF MEDIS","date":"2026-05-12","shift":"Shift 1","on":"19:50","off":"23:28","seconds":13080,"ts":1778518860000},{"id":"mig2fc3b13f10","staffId":"","name":"Fae Bellen","jabatan":"HRD","division":"DIREKSI & MANAJEMEN","date":"2026-05-12","shift":"Shift 1","on":"15:15","off":"16:12","seconds":3420,"ts":1778518860000},{"id":"mig2fc4d74774","staffId":"","name":"Fae Bellen","jabatan":"HRD","division":"DIREKSI & MANAJEMEN","date":"2026-05-12","shift":"Shift 2","on":"20:28","off":"21:48","seconds":4800,"ts":1778518920000},{"id":"mig2fc513e6f6","staffId":"","name":"Grizelle D Whitegate","jabatan":"KOMDIS","division":"DIREKSI & MANAJEMEN","date":"2026-05-12","shift":"Shift 1","on":"20:14","off":"20:50","seconds":2160,"ts":1778518860000},{"id":"mig2fc643b8eb","staffId":"","name":"Julian xavier","jabatan":"TRAINEE","division":"STAFF MEDIS","date":"2026-05-12","shift":"Shift 1","on":"21:00","off":"22:51","seconds":6660,"ts":1778518860000},{"id":"mig2fc774d53d","staffId":"","name":"Armel Quantum","jabatan":"TRAINEE","division":"STAFF MEDIS","date":"2026-05-13","shift":"Shift 1","on":"15:01","off":"16:03","seconds":3720,"ts":1778605260000},{"id":"mig2fc88fb170","staffId":"","name":"Armel Quantum","jabatan":"TRAINEE","division":"STAFF MEDIS","date":"2026-05-13","shift":"Shift 2","on":"16:26","off":"17:22","seconds":3360,"ts":1778605320000},{"id":"mig2fc93d7eef","staffId":"","name":"Carellia Jianyx Whitegate","jabatan":"DOKTER UMUM","division":"STAFF MEDIS","date":"2026-05-13","shift":"Shift 1","on":"21:25","off":"23:59","seconds":9240,"ts":1778605260000},{"id":"mig2fcaf568fd","staffId":"","name":"Dyvetta O. Kratawijaya","jabatan":"TRAINEE","division":"STAFF MEDIS","date":"2026-05-13","shift":"Shift 1","on":"20:13","off":"23:20","seconds":11220,"ts":1778605260000},{"id":"mig2fcb836d5a","staffId":"","name":"Grizelle D Whitegate","jabatan":"KOMDIS","division":"DIREKSI & MANAJEMEN","date":"2026-05-13","shift":"Shift 1","on":"00:02","off":"01:32","seconds":5400,"ts":1778605260000},{"id":"mig2fccaee52a","staffId":"","name":"Grizelle D Whitegate","jabatan":"KOMDIS","division":"DIREKSI & MANAJEMEN","date":"2026-05-13","shift":"Shift 2","on":"19:03","off":"20:49","seconds":6360,"ts":1778605320000},{"id":"mig2fcd138fc2","staffId":"","name":"Julian xavier","jabatan":"TRAINEE","division":"STAFF MEDIS","date":"2026-05-13","shift":"Shift 1","on":"21:50","off":"23:59","seconds":7740,"ts":1778605260000},{"id":"mig2fce769c2e","staffId":"","name":"LEON DACOSTA","jabatan":"DOKTER UMUM","division":"STAFF MEDIS","date":"2026-05-13","shift":"Shift 1","on":"21:48","off":"23:59","seconds":7860,"ts":1778605260000},{"id":"mig2fcff00684","staffId":"","name":"Armel Quantum","jabatan":"TRAINEE","division":"STAFF MEDIS","date":"2026-05-14","shift":"Shift 1","on":"14:20","off":"17:00","seconds":9600,"ts":1778691660000},{"id":"mig2fd03721ea","staffId":"","name":"Armel Quantum","jabatan":"TRAINEE","division":"STAFF MEDIS","date":"2026-05-14","shift":"Shift 2","on":"22:09","off":"23:59","seconds":6600,"ts":1778691720000},{"id":"mig2fd1c9e1a2","staffId":"","name":"Carellia Jianyx Whitegate","jabatan":"DOKTER UMUM","division":"STAFF MEDIS","date":"2026-05-14","shift":"Shift 1","on":"00:00","off":"00:11","seconds":660,"ts":1778691660000},{"id":"mig2fd2b20479","staffId":"","name":"Carellia Jianyx Whitegate","jabatan":"DOKTER UMUM","division":"STAFF MEDIS","date":"2026-05-14","shift":"Shift 2","on":"20:32","off":"22:54","seconds":8520,"ts":1778691720000},{"id":"mig2fd3225707","staffId":"","name":"Carellia Jianyx Whitegate","jabatan":"DOKTER UMUM","division":"STAFF MEDIS","date":"2026-05-14","shift":"Shift 3","on":"23:17","off":"23:59","seconds":2520,"ts":1778691780000},{"id":"mig2fd4b1a628","staffId":"","name":"Dyvetta O. Kratawijaya","jabatan":"TRAINEE","division":"STAFF MEDIS","date":"2026-05-14","shift":"Shift 1","on":"21:55","off":"23:59","seconds":7440,"ts":1778691660000},{"id":"mig2fd55ef427","staffId":"","name":"Fae Bellen","jabatan":"HRD","division":"DIREKSI & MANAJEMEN","date":"2026-05-14","shift":"Shift 1","on":"23:00","off":"23:59","seconds":3540,"ts":1778691660000},{"id":"mig2fd6b74bc2","staffId":"","name":"Grizelle D Whitegate","jabatan":"KOMDIS","division":"DIREKSI & MANAJEMEN","date":"2026-05-14","shift":"Shift 1","on":"00:49","off":"01:49","seconds":3600,"ts":1778691660000},{"id":"mig2fd79d6cc5","staffId":"","name":"Julian xavier","jabatan":"TRAINEE","division":"STAFF MEDIS","date":"2026-05-14","shift":"Shift 1","on":"21:23","off":"23:59","seconds":9360,"ts":1778691660000},{"id":"mig2fd82a140a","staffId":"","name":"LEON DACOSTA","jabatan":"DOKTER UMUM","division":"STAFF MEDIS","date":"2026-05-14","shift":"Shift 1","on":"00:01","off":"00:48","seconds":2820,"ts":1778691660000},{"id":"mig2fd90c6d76","staffId":"","name":"LEON DACOSTA","jabatan":"DOKTER UMUM","division":"STAFF MEDIS","date":"2026-05-14","shift":"Shift 2","on":"20:32","off":"23:59","seconds":12420,"ts":1778691720000},{"id":"mig2fdae749b4","staffId":"","name":"Armel Quantum","jabatan":"TRAINEE","division":"STAFF MEDIS","date":"2026-05-15","shift":"Shift 1","on":"22:38","off":"23:59","seconds":4860,"ts":1778778060000},{"id":"mig2fdbdbe377","staffId":"","name":"Carellia Jianyx Whitegate","jabatan":"DOKTER UMUM","division":"STAFF MEDIS","date":"2026-05-15","shift":"Shift 1","on":"00:00","off":"00:09","seconds":540,"ts":1778778060000},{"id":"mig2fdc468c5f","staffId":"","name":"Carellia Jianyx Whitegate","jabatan":"DOKTER UMUM","division":"STAFF MEDIS","date":"2026-05-15","shift":"Shift 2","on":"01:13","off":"01:56","seconds":2580,"ts":1778778120000},{"id":"mig2fdd0fb3e3","staffId":"","name":"Carellia Jianyx Whitegate","jabatan":"DOKTER UMUM","division":"STAFF MEDIS","date":"2026-05-15","shift":"Shift 3","on":"21:13","off":"23:59","seconds":9960,"ts":1778778180000},{"id":"mig2fdef70462","staffId":"","name":"Dyvetta O. Kratawijaya","jabatan":"TRAINEE","division":"STAFF MEDIS","date":"2026-05-15","shift":"Shift 1","on":"20:37","off":"23:59","seconds":12120,"ts":1778778060000},{"id":"mig2fdf3e5c01","staffId":"","name":"Fae Bellen","jabatan":"HRD","division":"DIREKSI & MANAJEMEN","date":"2026-05-15","shift":"Shift 1","on":"00:01","off":"01:00","seconds":3540,"ts":1778778060000},{"id":"mig2fe04f21c2","staffId":"","name":"Fae Bellen","jabatan":"HRD","division":"DIREKSI & MANAJEMEN","date":"2026-05-15","shift":"Shift 2","on":"20:20","off":"21:00","seconds":2400,"ts":1778778120000},{"id":"mig2fe1bb6bfa","staffId":"","name":"Grizelle D Whitegate","jabatan":"KOMDIS","division":"DIREKSI & MANAJEMEN","date":"2026-05-15","shift":"Shift 1","on":"20:15","off":"22:10","seconds":6900,"ts":1778778060000},{"id":"mig2fe21e31f4","staffId":"","name":"Jonathan Edward Sawyer Kylan Hudson","jabatan":"TRAINEE","division":"STAFF MEDIS","date":"2026-05-15","shift":"Shift 1","on":"15:49","off":"16:58","seconds":4140,"ts":1778778060000},{"id":"mig2fe3e5d74f","staffId":"","name":"Julian xavier","jabatan":"TRAINEE","division":"STAFF MEDIS","date":"2026-05-15","shift":"Shift 1","on":"00:00","off":"01:02","seconds":3720,"ts":1778778060000},{"id":"mig2fe4a9329c","staffId":"","name":"Julian xavier","jabatan":"TRAINEE","division":"STAFF MEDIS","date":"2026-05-15","shift":"Shift 2","on":"00:01","off":"01:25","seconds":5040,"ts":1778778120000},{"id":"mig2fe5c1f0bc","staffId":"","name":"Julian xavier","jabatan":"TRAINEE","division":"STAFF MEDIS","date":"2026-05-15","shift":"Shift 3","on":"15:23","off":"16:56","seconds":5580,"ts":1778778180000},{"id":"mig2fe657227e","staffId":"","name":"Julian xavier","jabatan":"TRAINEE","division":"STAFF MEDIS","date":"2026-05-15","shift":"Shift 4","on":"22:45","off":"23:59","seconds":4440,"ts":1778778240000},{"id":"mig2fe7a7dc20","staffId":"","name":"LEON DACOSTA","jabatan":"DOKTER UMUM","division":"STAFF MEDIS","date":"2026-05-15","shift":"Shift 1","on":"00:01","off":"00:51","seconds":3000,"ts":1778778060000},{"id":"mig2fe88a5ac9","staffId":"","name":"LEON DACOSTA","jabatan":"DOKTER UMUM","division":"STAFF MEDIS","date":"2026-05-15","shift":"Shift 2","on":"00:01","off":"01:24","seconds":4980,"ts":1778778120000},{"id":"mig2fe9318013","staffId":"","name":"LEON DACOSTA","jabatan":"DOKTER UMUM","division":"STAFF MEDIS","date":"2026-05-15","shift":"Shift 3","on":"20:48","off":"23:59","seconds":11460,"ts":1778778180000},{"id":"mig2fea02c4eb","staffId":"","name":"Armel Quantum","jabatan":"HRD","division":"DIREKSI & MANAJEMEN","date":"2026-05-16","shift":"Shift 1","on":"00:01","off":"01:01","seconds":3600,"ts":1778864460000},{"id":"mig2febab0af5","staffId":"","name":"Armel Quantum","jabatan":"HRD","division":"DIREKSI & MANAJEMEN","date":"2026-05-16","shift":"Shift 2","on":"20:52","off":"23:59","seconds":11220,"ts":1778864520000},{"id":"mig2fec4ae47b","staffId":"","name":"Carellia Jianyx Whitegate","jabatan":"HRD","division":"DIREKSI & MANAJEMEN","date":"2026-05-16","shift":"Shift 1","on":"00:12","off":"01:03","seconds":3060,"ts":1778864460000},{"id":"mig2fed21d479","staffId":"","name":"Carellia Jianyx Whitegate","jabatan":"HRD","division":"DIREKSI & MANAJEMEN","date":"2026-05-16","shift":"Shift 2","on":"21:05","off":"23:59","seconds":10440,"ts":1778864520000},{"id":"mig2fee8b2820","staffId":"","name":"Dyvetta O. Kratawijaya","jabatan":"TRAINEE","division":"STAFF MEDIS","date":"2026-05-16","shift":"Shift 1","on":"00:01","off":"01:00","seconds":3540,"ts":1778864460000},{"id":"mig2fef0d8b5d","staffId":"","name":"Dyvetta O. Kratawijaya","jabatan":"TRAINEE","division":"STAFF MEDIS","date":"2026-05-16","shift":"Shift 2","on":"19:41","off":"23:59","seconds":15480,"ts":1778864520000},{"id":"mig2ff0d46a81","staffId":"","name":"Fae Bellen","jabatan":"HRD","division":"DIREKSI & MANAJEMEN","date":"2026-05-16","shift":"Shift 1","on":"15:15","off":"17:20","seconds":7500,"ts":1778864460000},{"id":"mig2ff1ae56af","staffId":"","name":"Fae Bellen","jabatan":"HRD","division":"DIREKSI & MANAJEMEN","date":"2026-05-16","shift":"Shift 2","on":"19:30","off":"23:30","seconds":14400,"ts":1778864520000},{"id":"mig2ff258f9fb","staffId":"","name":"Julian xavier","jabatan":"TRAINEE","division":"STAFF MEDIS","date":"2026-05-16","shift":"Shift 1","on":"21:00","off":"23:05","seconds":7500,"ts":1778864460000},{"id":"mig2ff31b24c7","staffId":"","name":"LEON DACOSTA","jabatan":"TRAINEE","division":"STAFF MEDIS","date":"2026-05-16","shift":"Shift 1","on":"00:01","off":"01:24","seconds":4980,"ts":1778864460000},{"id":"mig2ff4d36f9a","staffId":"","name":"Viktor Moriarty","jabatan":"TRAINEE","division":"STAFF MEDIS","date":"2026-05-16","shift":"Shift 1","on":"15:30","off":"17:30","seconds":7200,"ts":1778864460000},{"id":"mig2ff520b54a","staffId":"","name":"Viktor Moriarty","jabatan":"TRAINEE","division":"STAFF MEDIS","date":"2026-05-16","shift":"Shift 2","on":"18:59","off":"21:26","seconds":8820,"ts":1778864520000},{"id":"mig2ff6605e6b","staffId":"","name":"Armel Quantum","jabatan":"HRD","division":"DIREKSI & MANAJEMEN","date":"2026-05-17","shift":"Shift 1","on":"00:01","off":"00:51","seconds":3000,"ts":1778950860000},{"id":"mig2ff73da72b","staffId":"","name":"Armel Quantum","jabatan":"HRD","division":"DIREKSI & MANAJEMEN","date":"2026-05-17","shift":"Shift 2","on":"15:08","off":"17:07","seconds":7140,"ts":1778950920000},{"id":"mig2ff865ac34","staffId":"","name":"Armel Quantum","jabatan":"HRD","division":"DIREKSI & MANAJEMEN","date":"2026-05-17","shift":"Shift 3","on":"20:05","off":"22:58","seconds":10380,"ts":1778950980000},{"id":"mig2ff9ee0447","staffId":"","name":"Carellia Jianyx Whitegate","jabatan":"HRD","division":"DIREKSI & MANAJEMEN","date":"2026-05-17","shift":"Shift 1","on":"00:00","off":"03:10","seconds":11400,"ts":1778950860000},{"id":"mig2ffaf63861","staffId":"","name":"Carellia Jianyx Whitegate","jabatan":"HRD","division":"DIREKSI & MANAJEMEN","date":"2026-05-17","shift":"Shift 2","on":"20:24","off":"21:34","seconds":4200,"ts":1778950920000},{"id":"mig2ffbc3e0c9","staffId":"","name":"Carellia Jianyx Whitegate","jabatan":"HRD","division":"DIREKSI & MANAJEMEN","date":"2026-05-17","shift":"Shift 3","on":"21:38","off":"22:21","seconds":2580,"ts":1778950980000},{"id":"mig2ffc5195c2","staffId":"","name":"Dyvetta O. Kratawijaya","jabatan":"TRAINEE","division":"STAFF MEDIS","date":"2026-05-17","shift":"Shift 1","on":"00:01","off":"01:20","seconds":4740,"ts":1778950860000},{"id":"mig2ffdac920d","staffId":"","name":"Dyvetta O. Kratawijaya","jabatan":"TRAINEE","division":"STAFF MEDIS","date":"2026-05-17","shift":"Shift 2","on":"19:25","off":"23:50","seconds":15900,"ts":1778950920000},{"id":"mig2ffe432041","staffId":"","name":"Julian xavier","jabatan":"TRAINEE","division":"STAFF MEDIS","date":"2026-05-17","shift":"Shift 1","on":"22:00","off":"23:59","seconds":7140,"ts":1778950860000},{"id":"mig2fff2fb738","staffId":"","name":"LEON DACOSTA","jabatan":"TRAINEE","division":"STAFF MEDIS","date":"2026-05-17","shift":"Shift 1","on":"21:05","off":"23:59","seconds":10440,"ts":1778950860000}],"archivedAt":1779037140000},{"key":"2026-05-18","start":"2026-05-18","end":"2026-05-24","records":[{"id":"mig3000e662bf","staffId":"","name":"Al Pratama","jabatan":"TRAINEE","division":"STAFF MEDIS","date":"2026-05-18","shift":"Shift 1","on":"08:10","off":"10:14","seconds":7440,"ts":1779037260000},{"id":"mig3001ff474e","staffId":"","name":"Al Pratama","jabatan":"TRAINEE","division":"STAFF MEDIS","date":"2026-05-18","shift":"Shift 2","on":"11:00","off":"17:20","seconds":22800,"ts":1779037320000},{"id":"mig3002008db0","staffId":"","name":"Al Pratama","jabatan":"TRAINEE","division":"STAFF MEDIS","date":"2026-05-18","shift":"Shift 3","on":"18:05","off":"21:00","seconds":10500,"ts":1779037380000},{"id":"mig3003bfce60","staffId":"","name":"Armel Quantum","jabatan":"HRD","division":"DIREKSI & MANAJEMEN","date":"2026-05-18","shift":"Shift 1","on":"15:31","off":"17:12","seconds":6060,"ts":1779037260000},{"id":"mig30044b1041","staffId":"","name":"Armel Quantum","jabatan":"HRD","division":"DIREKSI & MANAJEMEN","date":"2026-05-18","shift":"Shift 2","on":"18:58","off":"22:07","seconds":11340,"ts":1779037320000},{"id":"mig300568e0a7","staffId":"","name":"Dyvetta O. Kratawijaya","jabatan":"TRAINEE","division":"STAFF MEDIS","date":"2026-05-18","shift":"Shift 1","on":"19:26","off":"23:59","seconds":16380,"ts":1779037260000},{"id":"mig3006a0347f","staffId":"","name":"Julian xavier","jabatan":"TRAINEE","division":"STAFF MEDIS","date":"2026-05-18","shift":"Shift 1","on":"20:00","off":"23:59","seconds":14340,"ts":1779037260000},{"id":"mig30071bcacd","staffId":"","name":"LEON DACOSTA","jabatan":"TRAINEE","division":"STAFF MEDIS","date":"2026-05-18","shift":"Shift 1","on":"00:01","off":"03:18","seconds":11820,"ts":1779037260000},{"id":"mig30082a9a05","staffId":"","name":"LEON DACOSTA","jabatan":"TRAINEE","division":"STAFF MEDIS","date":"2026-05-18","shift":"Shift 2","on":"20:24","off":"23:59","seconds":12900,"ts":1779037320000},{"id":"mig3009af108f","staffId":"","name":"Armel Quantum","jabatan":"HRD","division":"DIREKSI & MANAJEMEN","date":"2026-05-19","shift":"Shift 1","on":"13:35","off":"17:06","seconds":12660,"ts":1779123660000},{"id":"mig300a90781a","staffId":"","name":"Dyvetta O. Kratawijaya","jabatan":"TRAINEE","division":"STAFF MEDIS","date":"2026-05-19","shift":"Shift 1","on":"00:01","off":"00:42","seconds":2460,"ts":1779123660000},{"id":"mig300ba57b46","staffId":"","name":"Dyvetta O. Kratawijaya","jabatan":"TRAINEE","division":"STAFF MEDIS","date":"2026-05-19","shift":"Shift 2","on":"20:18","off":"22:15","seconds":7020,"ts":1779123720000},{"id":"mig300c371cd5","staffId":"","name":"Fae Bellen","jabatan":"HRD","division":"DIREKSI & MANAJEMEN","date":"2026-05-19","shift":"Shift 1","on":"15:07","off":"17:22","seconds":8100,"ts":1779123660000},{"id":"mig300d0a76cb","staffId":"","name":"Fae Bellen","jabatan":"HRD","division":"DIREKSI & MANAJEMEN","date":"2026-05-19","shift":"Shift 2","on":"20:01","off":"23:48","seconds":13620,"ts":1779123720000},{"id":"mig300ed4c111","staffId":"","name":"Julian xavier","jabatan":"TRAINEE","division":"STAFF MEDIS","date":"2026-05-19","shift":"Shift 1","on":"20:30","off":"23:59","seconds":12540,"ts":1779123660000},{"id":"mig300fb7853b","staffId":"","name":"LEON DACOSTA","jabatan":"TRAINEE","division":"STAFF MEDIS","date":"2026-05-19","shift":"Shift 1","on":"00:01","off":"00:48","seconds":2820,"ts":1779123660000},{"id":"mig3010244b88","staffId":"","name":"LEON DACOSTA","jabatan":"TRAINEE","division":"STAFF MEDIS","date":"2026-05-19","shift":"Shift 2","on":"22:10","off":"23:59","seconds":6540,"ts":1779123720000},{"id":"mig301158236e","staffId":"","name":"Viktor Moriarty","jabatan":"TRAINEE","division":"STAFF MEDIS","date":"2026-05-19","shift":"Shift 1","on":"11:26","off":"17:30","seconds":21840,"ts":1779123660000},{"id":"mig3012455859","staffId":"","name":"Viktor Moriarty","jabatan":"TRAINEE","division":"STAFF MEDIS","date":"2026-05-19","shift":"Shift 2","on":"19:41","off":"20:34","seconds":3180,"ts":1779123720000},{"id":"mig3013fdf23a","staffId":"","name":"Viktor Moriarty","jabatan":"TRAINEE","division":"STAFF MEDIS","date":"2026-05-19","shift":"Shift 3","on":"20:41","off":"21:27","seconds":2760,"ts":1779123780000},{"id":"mig3014cb9322","staffId":"","name":"Al Pratama","jabatan":"TRAINEE","division":"STAFF MEDIS","date":"2026-05-20","shift":"Shift 1","on":"06:50","off":"08:10","seconds":4800,"ts":1779210060000},{"id":"mig301589208d","staffId":"","name":"Al Pratama","jabatan":"TRAINEE","division":"STAFF MEDIS","date":"2026-05-20","shift":"Shift 2","on":"13:50","off":"16:15","seconds":8700,"ts":1779210120000},{"id":"mig301668affa","staffId":"","name":"Armel Quantum","jabatan":"HRD","division":"DIREKSI & MANAJEMEN","date":"2026-05-20","shift":"Shift 1","on":"00:00","off":"00:20","seconds":1200,"ts":1779210060000},{"id":"mig3017c2500c","staffId":"","name":"Armel Quantum","jabatan":"HRD","division":"DIREKSI & MANAJEMEN","date":"2026-05-20","shift":"Shift 2","on":"15:35","off":"17:15","seconds":6000,"ts":1779210120000},{"id":"mig301826e962","staffId":"","name":"Armel Quantum","jabatan":"HRD","division":"DIREKSI & MANAJEMEN","date":"2026-05-20","shift":"Shift 3","on":"19:39","off":"23:40","seconds":14460,"ts":1779210180000},{"id":"mig3019874be2","staffId":"","name":"Dyvetta O. Kratawijaya","jabatan":"TRAINEE","division":"STAFF MEDIS","date":"2026-05-20","shift":"Shift 1","on":"20:45","off":"23:40","seconds":10500,"ts":1779210060000},{"id":"mig301a143182","staffId":"","name":"Fae Bellen","jabatan":"HRD","division":"DIREKSI & MANAJEMEN","date":"2026-05-20","shift":"Shift 1","on":"20:52","off":"22:55","seconds":7380,"ts":1779210060000},{"id":"mig301b9b42e0","staffId":"","name":"Julian xavier","jabatan":"TRAINEE","division":"STAFF MEDIS","date":"2026-05-20","shift":"Shift 1","on":"23:45","off":"23:59","seconds":840,"ts":1779210060000},{"id":"mig301c48fb8a","staffId":"","name":"LEON DACOSTA","jabatan":"TRAINEE","division":"STAFF MEDIS","date":"2026-05-20","shift":"Shift 1","on":"00:01","off":"00:32","seconds":1860,"ts":1779210060000},{"id":"mig301da88a87","staffId":"","name":"Viktor Moriarty","jabatan":"TRAINEE","division":"STAFF MEDIS","date":"2026-05-20","shift":"Shift 1","on":"12:25","off":"14:04","seconds":5940,"ts":1779210060000},{"id":"mig301e51c162","staffId":"","name":"Al Pratama","jabatan":"TRAINEE","division":"STAFF MEDIS","date":"2026-05-21","shift":"Shift 1","on":"09:41","off":"11:17","seconds":5760,"ts":1779296460000},{"id":"mig301f3740c5","staffId":"","name":"Al Pratama","jabatan":"TRAINEE","division":"STAFF MEDIS","date":"2026-05-21","shift":"Shift 2","on":"12:28","off":"16:24","seconds":14160,"ts":1779296520000},{"id":"mig3020ba3bbf","staffId":"","name":"Armel Quantum","jabatan":"HRD","division":"DIREKSI & MANAJEMEN","date":"2026-05-21","shift":"Shift 1","on":"15:22","off":"17:04","seconds":6120,"ts":1779296460000},{"id":"mig3021813843","staffId":"","name":"Armel Quantum","jabatan":"HRD","division":"DIREKSI & MANAJEMEN","date":"2026-05-21","shift":"Shift 2","on":"20:08","off":"23:22","seconds":11640,"ts":1779296520000},{"id":"mig30226e94d3","staffId":"","name":"Carellia Jianyx Whitegate","jabatan":"HRD","division":"DIREKSI & MANAJEMEN","date":"2026-05-21","shift":"Shift 1","on":"20:18","off":"23:16","seconds":10680,"ts":1779296460000},{"id":"mig3023cc762b","staffId":"","name":"Dyvetta O. Kratawijaya","jabatan":"TRAINEE","division":"STAFF MEDIS","date":"2026-05-21","shift":"Shift 1","on":"20:28","off":"23:50","seconds":12120,"ts":1779296460000},{"id":"mig3024bc8092","staffId":"","name":"Julian xavier","jabatan":"TRAINEE","division":"STAFF MEDIS","date":"2026-05-21","shift":"Shift 1","on":"00:00","off":"02:09","seconds":7740,"ts":1779296460000},{"id":"mig3025fc1314","staffId":"","name":"Viktor Moriarty","jabatan":"TRAINEE","division":"STAFF MEDIS","date":"2026-05-21","shift":"Shift 1","on":"00:13","off":"00:37","seconds":1440,"ts":1779296460000},{"id":"mig3026998099","staffId":"","name":"Al Pratama","jabatan":"TRAINEE","division":"STAFF MEDIS","date":"2026-05-22","shift":"Shift 1","on":"13:07","off":"16:39","seconds":12720,"ts":1779382860000},{"id":"mig3027013cfd","staffId":"","name":"Armel Quantum","jabatan":"HRD","division":"DIREKSI & MANAJEMEN","date":"2026-05-22","shift":"Shift 1","on":"13:37","off":"13:50","seconds":780,"ts":1779382860000},{"id":"mig302894eb4b","staffId":"","name":"Armel Quantum","jabatan":"HRD","division":"DIREKSI & MANAJEMEN","date":"2026-05-22","shift":"Shift 2","on":"14:11","off":"14:39","seconds":1680,"ts":1779382920000},{"id":"mig3029cf63f3","staffId":"","name":"Armel Quantum","jabatan":"HRD","division":"DIREKSI & MANAJEMEN","date":"2026-05-22","shift":"Shift 3","on":"14:43","off":"17:05","seconds":8520,"ts":1779382980000},{"id":"mig302a73adaa","staffId":"","name":"Armel Quantum","jabatan":"HRD","division":"DIREKSI & MANAJEMEN","date":"2026-05-22","shift":"Shift 4","on":"21:00","off":"23:00","seconds":7200,"ts":1779383040000},{"id":"mig302b1c7e90","staffId":"","name":"Carellia Jianyx Whitegate","jabatan":"HRD","division":"DIREKSI & MANAJEMEN","date":"2026-05-22","shift":"Shift 1","on":"20:57","off":"22:41","seconds":6240,"ts":1779382860000},{"id":"mig302c43670d","staffId":"","name":"Julian xavier","jabatan":"TRAINEE","division":"STAFF MEDIS","date":"2026-05-22","shift":"Shift 1","on":"20:40","off":"23:41","seconds":10860,"ts":1779382860000}],"archivedAt":1779641940000},{"key":"2026-05-25","start":"2026-05-25","end":"2026-05-31","records":[{"id":"mig302d38718a","staffId":"","name":"Carellia Jianyx Whitegate","jabatan":"HRD","division":"DIREKSI & MANAJEMEN","date":"2026-05-29","shift":"Shift 1","on":"20:30","off":"21:30","seconds":3600,"ts":1779987660000}],"archivedAt":1780246740000},{"key":"2026-06-08","start":"2026-06-08","end":"2026-06-14","records":[{"id":"mig302e2e4361","staffId":"mig0005df989a","name":"Kiyan Nagasaki","jabatan":"CO-ASS","division":"STAFF MEDIS","date":"2026-06-08","shift":"Shift 1","on":"19:29","off":"21:19","seconds":6600,"ts":1780851660000},{"id":"mig302f152ec2","staffId":"mig0005df989a","name":"Kiyan Nagasaki","jabatan":"CO-ASS","division":"STAFF MEDIS","date":"2026-06-08","shift":"Shift 2","on":"22:59","off":"23:59","seconds":3600,"ts":1780851720000},{"id":"mig30303a4117","staffId":"","name":"Ryuu Kaito","jabatan":"TRAINEE","division":"STAFF MEDIS","date":"2026-06-08","shift":"Shift 1","on":"19:09","off":"22:11","seconds":10920,"ts":1780851660000},{"id":"mig3031059c73","staffId":"mig0004694f16","name":"Catalina De Sugar","jabatan":"CO-ASS","division":"STAFF MEDIS","date":"2026-06-09","shift":"Shift 1","on":"21:42","off":"22:00","seconds":1080,"ts":1780938060000},{"id":"mig30324dd16e","staffId":"mig0004694f16","name":"Catalina De Sugar","jabatan":"CO-ASS","division":"STAFF MEDIS","date":"2026-06-09","shift":"Shift 2","on":"23:12","off":"23:59","seconds":2820,"ts":1780938120000},{"id":"mig3033d478d0","staffId":"","name":"Ryuu Kaito","jabatan":"TRAINEE","division":"STAFF MEDIS","date":"2026-06-09","shift":"Shift 1","on":"17:03","off":"21:10","seconds":14820,"ts":1780938060000},{"id":"mig3034bf586b","staffId":"mig0004694f16","name":"Catalina De Sugar","jabatan":"CO-ASS","division":"STAFF MEDIS","date":"2026-06-10","shift":"Shift 1","on":"00:00","off":"02:33","seconds":9180,"ts":1781024460000},{"id":"mig303536af0c","staffId":"mig0004694f16","name":"Catalina De Sugar","jabatan":"CO-ASS","division":"STAFF MEDIS","date":"2026-06-10","shift":"Shift 2","on":"18:47","off":"21:42","seconds":10500,"ts":1781024520000},{"id":"mig30365cf029","staffId":"","name":"Kathrina De Sugar","jabatan":"TRAINEE","division":"STAFF MEDIS","date":"2026-06-10","shift":"Shift 1","on":"19:22","off":"21:12","seconds":6600,"ts":1781024460000},{"id":"mig3037f34bc4","staffId":"","name":"Kathrina De Sugar","jabatan":"TRAINEE","division":"STAFF MEDIS","date":"2026-06-10","shift":"Shift 2","on":"20:30","off":"22:30","seconds":7200,"ts":1781024520000},{"id":"mig3038ce343a","staffId":"","name":"Pey'D Carrera","jabatan":"TRAINEE","division":"STAFF MEDIS","date":"2026-06-10","shift":"Shift 1","on":"20:08","off":"22:28","seconds":8400,"ts":1781024460000},{"id":"mig3039f3ce56","staffId":"mig0004694f16","name":"Catalina De Sugar","jabatan":"CO-ASS","division":"STAFF MEDIS","date":"2026-06-11","shift":"Shift 1","on":"00:42","off":"02:59","seconds":8220,"ts":1781110860000},{"id":"mig303a8cad1e","staffId":"","name":"Pey'D Carrera","jabatan":"TRAINEE","division":"STAFF MEDIS","date":"2026-06-11","shift":"Shift 1","on":"20:30","off":"23:03","seconds":9180,"ts":1781110860000},{"id":"mig303b32203f","staffId":"mig0004694f16","name":"Catalina De Sugar","jabatan":"CO-ASS","division":"STAFF MEDIS","date":"2026-06-12","shift":"Shift 1","on":"18:29","off":"23:59","seconds":19800,"ts":1781197260000},{"id":"mig303c153e5c","staffId":"","name":"Pey'D Carrera","jabatan":"TRAINEE","division":"STAFF MEDIS","date":"2026-06-12","shift":"Shift 1","on":"19:40","off":"20:40","seconds":3600,"ts":1781197260000},{"id":"mig303d67c6c8","staffId":"mig0004694f16","name":"Catalina De Sugar","jabatan":"CO-ASS","division":"STAFF MEDIS","date":"2026-06-13","shift":"Shift 1","on":"00:00","off":"00:24","seconds":1440,"ts":1781283660000},{"id":"mig303ea9b970","staffId":"mig0004694f16","name":"Catalina De Sugar","jabatan":"CO-ASS","division":"STAFF MEDIS","date":"2026-06-13","shift":"Shift 2","on":"18:00","off":"23:59","seconds":21540,"ts":1781283720000},{"id":"mig303f587fef","staffId":"mig0001780106","name":"Alicia Clarissa De Sugar","jabatan":"CEO","division":"DIREKSI & MANAJEMEN","date":"2026-06-14","shift":"Shift 1","on":"12:00","off":"14:00","seconds":7200,"ts":1781370060000},{"id":"mig3040f5889c","staffId":"mig0004694f16","name":"Catalina De Sugar","jabatan":"CO-ASS","division":"STAFF MEDIS","date":"2026-06-14","shift":"Shift 1","on":"00:00","off":"00:50","seconds":3000,"ts":1781370060000},{"id":"mig3041a683b7","staffId":"mig0004694f16","name":"Catalina De Sugar","jabatan":"CO-ASS","division":"STAFF MEDIS","date":"2026-06-14","shift":"Shift 2","on":"19:00","off":"23:59","seconds":17940,"ts":1781370120000},{"id":"mig304249a8e9","staffId":"","name":"Kathrina De Sugar","jabatan":"TRAINEE","division":"STAFF MEDIS","date":"2026-06-14","shift":"Shift 1","on":"14:10","off":"16:10","seconds":7200,"ts":1781370060000}],"archivedAt":1781456340000}],"passwordHash":"8e9b4e74c1b95cd343b4475d42158836:30f6087dbca979878e385bfe861ee6713d32fc0228089fa09d2694d0053f19cbc82211314aab3ed9b72403bf5938db67037792459d96750162ca942b0bc1e74a","payroll":{"jab":{"CEO":{"rate":0,"otThreshold":0,"otBonusPct":0},"DIREKTUR":{"rate":0,"otThreshold":0,"otBonusPct":0},"WAKIL DIREKTUR":{"rate":0,"otThreshold":0,"otBonusPct":0},"SEKBEN":{"rate":0,"otThreshold":0,"otBonusPct":0},"KABID KOMDIS":{"rate":0,"otThreshold":0,"otBonusPct":0},"KOMDIS":{"rate":0,"otThreshold":0,"otBonusPct":0},"KABID HRD":{"rate":0,"otThreshold":0,"otBonusPct":0},"HRD":{"rate":0,"otThreshold":0,"otBonusPct":0},"KA.LABORAN":{"rate":0,"otThreshold":0,"otBonusPct":0},"MANAJEMEN LAB":{"rate":0,"otThreshold":0,"otBonusPct":0},"DOKTER SPESIALIS":{"rate":0,"otThreshold":0,"otBonusPct":0},"DOKTER UMUM":{"rate":0,"otThreshold":0,"otBonusPct":0},"CO-ASS":{"rate":0,"otThreshold":0,"otBonusPct":0},"TRAINEE":{"rate":0,"otThreshold":0,"otBonusPct":0}}}}